Verilog Testing/src/sqrt_root.v
`timescale 1ns/1ps

// NOTE: This is an integer square root. so results like 2.7 are trunicated to 2.
module sqrt_root (
    input  wire        clk,
    input  wire        rst,
    input  wire        start,
    input  wire [63:0] in_value,
    output reg  [63:0] root,
    output reg         done,
    output reg         busy
);

    reg [63:0] val;
    reg [63:0] res;
    reg [63:0] bit_mask;
    reg [6:0]  i;

    always @(posedge clk) begin
        if (rst) begin
            val  <= 64'd0;
            res  <= 64'd0;
            bit_mask <= 64'd0;
            i    <= 7'd0;
            root <= 64'd0;
            done <= 1'b0;
            busy <= 1'b0;
        end else begin
            if (start && !busy) begin
                val  <= in_value;
                res  <= 64'd0;
                bit_mask <= 64'h4000_0000_0000_0000;
                i    <= 7'd0;
                done <= 1'b0;
                busy <= 1'b1;
            end else if (busy) begin
                if (i == 7'd0 && bit_mask > val) begin
                    bit_mask <= (bit_mask >> 2);
                end else if (i < 7'd32 && bit_mask != 64'd0) begin
                    if (val >= (res + bit_mask)) begin
                        val <= val - (res + bit_mask);
                        res <= (res >> 1) + bit_mask;
                    end else begin
                        res <= (res >> 1);
                    end
                    bit_mask <= (bit_mask >> 2);
                    i   <= i + 1'b1;
                end else begin
                    root <= res;
                    done <= 1'b1;
                    busy <= 1'b0;
                end
            end
        end
    end

endmodule

Verilog Testing/tb/sqrt_root_tb.v
`timescale 1ns/1ps
`define START_TIMEOUT_CYCLES 50
`define DONE_TIMEOUT_CYCLES  250

module sqrt_root_tb;
    reg         clk;
    reg         rst;
    reg         start;
    reg  [63:0] in_value;
    wire [63:0] root;
    wire        done;
    wire        busy;

    integer     errors;

    sqrt_root dut (
        .clk(clk),
        .rst(rst),
        .start(start),
        .in_value(in_value),
        .root(root),
        .done(done),
        .busy(busy)
    );

    always #5 clk = ~clk; // period = 10ns => 100MHz

    function [63:0] ref_sqrt64;
        input [63:0] x;
        reg   [63:0] cand;
        reg   [63:0] ans;
        reg  [127:0] sq;
        integer k;
        begin
            ans = 64'd0;
            for (k = 31; k >= 0; k = k - 1) begin
                cand = ans | (64'd1 << k);
                sq   = cand * cand;
                if (sq <= x) begin
                    ans = cand;
                end
            end
            ref_sqrt64 = ans;
        end
    endfunction

    task run_case;
        input [63:0] value;
        reg   [63:0] exp;
        integer timeout;
        begin
            exp = ref_sqrt64(value);

            @(posedge clk);
            in_value <= value;
            start    <= 1'b1;
            @(posedge clk);
            start    <= 1'b0;

            timeout = 0;
            while (!busy && timeout < `START_TIMEOUT_CYCLES) begin
                @(posedge clk);
                timeout = timeout + 1;
            end

            timeout = 0;
            while ((busy || !done) && timeout < `DONE_TIMEOUT_CYCLES) begin
                @(posedge clk);
                timeout = timeout + 1;
            end

            if (busy || !done) begin
                $display("TIMEOUT: value=%0d", value);
                errors = errors + 1;
            end else if (root !== exp) begin
                $display("FAIL: value=%0d expected=%0d got=%0d", value, exp, root);
                errors = errors + 1;
            end else begin
                $display("PASS: value=%0d root=%0d cycles=%0d", value, root, timeout);
            end

            @(posedge clk);
        end
    endtask

    integer n;
    reg [63:0] rnd;

    initial begin
        $dumpfile("outputs/sqrt_root_tb.vcd");
        $dumpvars(0, sqrt_root_tb);

        clk      = 1'b0;
        rst      = 1'b1;
        start    = 1'b0;
        in_value = 64'd0;
        errors   = 0;

        repeat (3) @(posedge clk);
        rst = 1'b0;

        run_case(64'd0);
        run_case(64'd1);
        run_case(64'd2);
        run_case(64'd3);
        run_case(64'd4);
        run_case(64'd15);
        run_case(64'd16);
        run_case(64'd17);
        run_case(64'd24);
        run_case(64'd25);
        run_case(64'd26);
        run_case(64'd1000);
        run_case(64'd1_000_000_000);
        run_case(64'h0000_0001_0000_0000);
        run_case(64'h7FFF_FFFF_FFFF_FFFF);
        run_case(64'hFFFF_FFFF_FFFF_FFFF);

        for (n = 0; n < 20; n = n + 1) begin
            rnd = {$random, $random};
            run_case(rnd);
        end

        if (errors == 0) begin
            $display("ALL TESTS PASSED");
        end else begin
            $display("TESTS FAILED: %0d errors", errors);
        end

        $finish;
    end
endmodule

Verilog Testing/outputs/sqrt_root_tb.vcd
$date
	Wed Feb 25 16:43:00 2026
$end
$version
	Icarus Verilog
$end
$timescale
	1ps
$end
$scope module sqrt_root_tb $end
$var wire 64 ! root [63:0] $end
$var wire 1 " done $end
$var wire 1 # busy $end
$var reg 1 $ clk $end
$var reg 64 % in_value [63:0] $end
$var reg 64 & rnd [63:0] $end
$var reg 1 ' rst $end
$var reg 1 ( start $end
$var integer 32 ) errors [31:0] $end
$var integer 32 * n [31:0] $end
$scope function ref_sqrt64 $end
$var reg 64 + ans [63:0] $end
$var reg 64 , cand [63:0] $end
$var reg 128 - sq [127:0] $end
$var reg 64 . x [63:0] $end
$var integer 32 / k [31:0] $end
$upscope $end
$scope module dut $end
$var wire 1 $ clk $end
$var wire 64 0 in_value [63:0] $end
$var wire 1 ' rst $end
$var wire 1 ( start $end
$var reg 64 1 bit_mask [63:0] $end
$var reg 1 # busy $end
$var reg 1 " done $end
$var reg 7 2 i [6:0] $end
$var reg 64 3 res [63:0] $end
$var reg 64 4 root [63:0] $end
$var reg 64 5 val [63:0] $end
$upscope $end
$scope task run_case $end
$var reg 64 6 exp [63:0] $end
$var reg 64 7 value [63:0] $end
$var integer 32 8 timeout [31:0] $end
$upscope $end
$upscope $end
$enddefinitions $end
$comment Show the parameter values. $end
$dumpall
$end
#0
$dumpvars
bx 8
bx 7
bx 6
bx 5
bx 4
bx 3
bx 2
bx 1
b0 0
bx /
bx .
bx -
bx ,
bx +
bx *
b0 )
0(
1'
bx &
b0 %
0$
x#
x"
bx !
$end
#5000
0#
0"
b0 !
b0 4
b0 2
b0 1
b0 3
b0 5
1$
#10000
0$
#15000
1$
#20000
0$
#25000
b0 6
b1 -
b1 ,
b11111111111111111111111111111111 /
b0 +
b0 .
b0 7
0'
1$
#30000
0$
#35000
1(
1$
#40000
0$
#45000
0(
1#
b100000000000000000000000000000000000000000000000000000000000000 1
b0 8
1$
#50000
0$
#55000
b1000000000000000000000000000000000000000000000000000000000000 1
b0 8
1$
#60000
0$
#65000
b10000000000000000000000000000000000000000000000000000000000 1
b1 8
1$
#70000
0$
#75000
b100000000000000000000000000000000000000000000000000000000 1
b10 8
1$
#80000
0$
#85000
b1000000000000000000000000000000000000000000000000000000 1
b11 8
1$
#90000
0$
#95000
b10000000000000000000000000000000000000000000000000000 1
b100 8
1$
#100000
0$
#105000
b100000000000000000000000000000000000000000000000000 1
b101 8
1$
#110000
0$
#115000
b1000000000000000000000000000000000000000000000000 1
b110 8
1$
#120000
0$
#125000
b10000000000000000000000000000000000000000000000 1
b111 8
1$
#130000
0$
#135000
b100000000000000000000000000000000000000000000 1
b1000 8
1$
#140000
0$
#145000
b1000000000000000000000000000000000000000000 1
b1001 8
1$
#150000
0$
#155000
b10000000000000000000000000000000000000000 1
b1010 8
1$
#160000
0$
#165000
b100000000000000000000000000000000000000 1
b1011 8
1$
#170000
0$
#175000
b1000000000000000000000000000000000000 1
b1100 8
1$
#180000
0$
#185000
b10000000000000000000000000000000000 1
b1101 8
1$
#190000
0$
#195000
b100000000000000000000000000000000 1
b1110 8
1$
#200000
0$
#205000
b1000000000000000000000000000000 1
b1111 8
1$
#210000
0$
#215000
b10000000000000000000000000000 1
b10000 8
1$
#220000
0$
#225000
b100000000000000000000000000 1
b10001 8
1$
#230000
0$
#235000
b1000000000000000000000000 1
b10010 8
1$
#240000
0$
#245000
b10000000000000000000000 1
b10011 8
1$
#250000
0$
#255000
b100000000000000000000 1
b10100 8
1$
#260000
0$
#265000
b1000000000000000000 1
b10101 8
1$
#270000
0$
#275000
b10000000000000000 1
b10110 8
1$
#280000
0$
#285000
b100000000000000 1
b10111 8
1$
#290000
0$
#295000
b1000000000000 1
b11000 8
1$
#300000
0$
#305000
b10000000000 1
b11001 8
1$
#310000
0$
#315000
b100000000 1
b11010 8
1$
#320000
0$
#325000
b1000000 1
b11011 8
1$
#330000
0$
#335000
b10000 1
b11100 8
1$
#340000
0$
#345000
b100 1
b11101 8
1$
#350000
0$
#355000
b1 1
b11110 8
1$
#360000
0$
#365000
b0 1
b11111 8
1$
#370000
0$
#375000
0#
1"
b100000 8
1$
#380000
0$
#385000
b100001 8
1$
#390000
0$
#395000
b1 6
b1 +
b1 -
b1 ,
b11111111111111111111111111111111 /
b1 .
b1 7
1$
#400000
0$
#405000
1(
b1 %
b1 0
1$
#410000
0$
#415000
0(
1#
0"
b100000000000000000000000000000000000000000000000000000000000000 1
b1 5
b0 8
1$
#420000
0$
#425000
b1000000000000000000000000000000000000000000000000000000000000 1
b0 8
1$
#430000
0$
#435000
b10000000000000000000000000000000000000000000000000000000000 1
b1 8
1$
#440000
0$
#445000
b100000000000000000000000000000000000000000000000000000000 1
b10 8
1$
#450000
0$
#455000
b1000000000000000000000000000000000000000000000000000000 1
b11 8
1$
#460000
0$
#465000
b10000000000000000000000000000000000000000000000000000 1
b100 8
1$
#470000
0$
#475000
b100000000000000000000000000000000000000000000000000 1
b101 8
1$
#480000
0$
#485000
b1000000000000000000000000000000000000000000000000 1
b110 8
1$
#490000
0$
#495000
b10000000000000000000000000000000000000000000000 1
b111 8
1$
#500000
0$
#505000
b100000000000000000000000000000000000000000000 1
b1000 8
1$
#510000
0$
#515000
b1000000000000000000000000000000000000000000 1
b1001 8
1$
#520000
0$
#525000
b10000000000000000000000000000000000000000 1
b1010 8
1$
#530000
0$
#535000
b100000000000000000000000000000000000000 1
b1011 8
1$
#540000
0$
#545000
b1000000000000000000000000000000000000 1
b1100 8
1$
#550000
0$
#555000
b10000000000000000000000000000000000 1
b1101 8
1$
#560000
0$
#565000
b100000000000000000000000000000000 1
b1110 8
1$
#570000
0$
#575000
b1000000000000000000000000000000 1
b1111 8
1$
#580000
0$
#585000
b10000000000000000000000000000 1
b10000 8
1$
#590000
0$
#595000
b100000000000000000000000000 1
b10001 8
1$
#600000
0$
#605000
b1000000000000000000000000 1
b10010 8
1$
#610000
0$
#615000
b10000000000000000000000 1
b10011 8
1$
#620000
0$
#625000
b100000000000000000000 1
b10100 8
1$
#630000
0$
#635000
b1000000000000000000 1
b10101 8
1$
#640000
0$
#645000
b10000000000000000 1
b10110 8
1$
#650000
0$
#655000
b100000000000000 1
b10111 8
1$
#660000
0$
#665000
b1000000000000 1
b11000 8
1$
#670000
0$
#675000
b10000000000 1
b11001 8
1$
#680000
0$
#685000
b100000000 1
b11010 8
1$
#690000
0$
#695000
b1000000 1
b11011 8
1$
#700000
0$
#705000
b10000 1
b11100 8
1$
#710000
0$
#715000
b100 1
b11101 8
1$
#720000
0$
#725000
b1 1
b11110 8
1$
#730000
0$
#735000
b1 2
b0 1
b1 3
b0 5
b11111 8
1$
#740000
0$
#745000
0#
1"
b1 !
b1 4
b100000 8
1$
#750000
0$
#755000
b100001 8
1$
#760000
0$
#765000
b1 -
b1 ,
b11111111111111111111111111111111 /
b1 +
b10 .
b10 7
1$
#770000
0$
#775000
1(
b10 %
b10 0
1$
#780000
0$
#785000
0(
1#
0"
b0 2
b100000000000000000000000000000000000000000000000000000000000000 1
b0 3
b10 5
b0 8
1$
#790000
0$
#795000
b1000000000000000000000000000000000000000000000000000000000000 1
b0 8
1$
#800000
0$
#805000
b10000000000000000000000000000000000000000000000000000000000 1
b1 8
1$
#810000
0$
#815000
b100000000000000000000000000000000000000000000000000000000 1
b10 8
1$
#820000
0$
#825000
b1000000000000000000000000000000000000000000000000000000 1
b11 8
1$
#830000
0$
#835000
b10000000000000000000000000000000000000000000000000000 1
b100 8
1$
#840000
0$
#845000
b100000000000000000000000000000000000000000000000000 1
b101 8
1$
#850000
0$
#855000
b1000000000000000000000000000000000000000000000000 1
b110 8
1$
#860000
0$
#865000
b10000000000000000000000000000000000000000000000 1
b111 8
1$
#870000
0$
#875000
b100000000000000000000000000000000000000000000 1
b1000 8
1$
#880000
0$
#885000
b1000000000000000000000000000000000000000000 1
b1001 8
1$
#890000
0$
#895000
b10000000000000000000000000000000000000000 1
b1010 8
1$
#900000
0$
#905000
b100000000000000000000000000000000000000 1
b1011 8
1$
#910000
0$
#915000
b1000000000000000000000000000000000000 1
b1100 8
1$
#920000
0$
#925000
b10000000000000000000000000000000000 1
b1101 8
1$
#930000
0$
#935000
b100000000000000000000000000000000 1
b1110 8
1$
#940000
0$
#945000
b1000000000000000000000000000000 1
b1111 8
1$
#950000
0$
#955000
b10000000000000000000000000000 1
b10000 8
1$
#960000
0$
#965000
b100000000000000000000000000 1
b10001 8
1$
#970000
0$
#975000
b1000000000000000000000000 1
b10010 8
1$
#980000
0$
#985000
b10000000000000000000000 1
b10011 8
1$
#990000
0$
#995000
b100000000000000000000 1
b10100 8
1$
#1000000
0$
#1005000
b1000000000000000000 1
b10101 8
1$
#1010000
0$
#1015000
b10000000000000000 1
b10110 8
1$
#1020000
0$
#1025000
b100000000000000 1
b10111 8
1$
#1030000
0$
#1035000
b1000000000000 1
b11000 8
1$
#1040000
0$
#1045000
b10000000000 1
b11001 8
1$
#1050000
0$
#1055000
b100000000 1
b11010 8
1$
#1060000
0$
#1065000
b1000000 1
b11011 8
1$
#1070000
0$
#1075000
b10000 1
b11100 8
1$
#1080000
0$
#1085000
b100 1
b11101 8
1$
#1090000
0$
#1095000
b1 1
b11110 8
1$
#1100000
0$
#1105000
b1 2
b0 1
b1 3
b1 5
b11111 8
1$
#1110000
0$
#1115000
0#
1"
b100000 8
1$
#1120000
0$
#1125000
b100001 8
1$
#1130000
0$
#1135000
b1 -
b1 ,
b11111111111111111111111111111111 /
b1 +
b11 .
b11 7
1$
#1140000
0$
#1145000
1(
b11 %
b11 0
1$
#1150000
0$
#1155000
0(
1#
0"
b0 2
b100000000000000000000000000000000000000000000000000000000000000 1
b0 3
b11 5
b0 8
1$
#1160000
0$
#1165000
b1000000000000000000000000000000000000000000000000000000000000 1
b0 8
1$
#1170000
0$
#1175000
b10000000000000000000000000000000000000000000000000000000000 1
b1 8
1$
#1180000
0$
#1185000
b100000000000000000000000000000000000000000000000000000000 1
b10 8
1$
#1190000
0$
#1195000
b1000000000000000000000000000000000000000000000000000000 1
b11 8
1$
#1200000
0$
#1205000
b10000000000000000000000000000000000000000000000000000 1
b100 8
1$
#1210000
0$
#1215000
b100000000000000000000000000000000000000000000000000 1
b101 8
1$
#1220000
0$
#1225000
b1000000000000000000000000000000000000000000000000 1
b110 8
1$
#1230000
0$
#1235000
b10000000000000000000000000000000000000000000000 1
b111 8
1$
#1240000
0$
#1245000
b100000000000000000000000000000000000000000000 1
b1000 8
1$
#1250000
0$
#1255000
b1000000000000000000000000000000000000000000 1
b1001 8
1$
#1260000
0$
#1265000
b10000000000000000000000000000000000000000 1
b1010 8
1$
#1270000
0$
#1275000
b100000000000000000000000000000000000000 1
b1011 8
1$
#1280000
0$
#1285000
b1000000000000000000000000000000000000 1
b1100 8
1$
#1290000
0$
#1295000
b10000000000000000000000000000000000 1
b1101 8
1$
#1300000
0$
#1305000
b100000000000000000000000000000000 1
b1110 8
1$
#1310000
0$
#1315000
b1000000000000000000000000000000 1
b1111 8
1$
#1320000
0$
#1325000
b10000000000000000000000000000 1
b10000 8
1$
#1330000
0$
#1335000
b100000000000000000000000000 1
b10001 8
1$
#1340000
0$
#1345000
b1000000000000000000000000 1
b10010 8
1$
#1350000
0$
#1355000
b10000000000000000000000 1
b10011 8
1$
#1360000
0$
#1365000
b100000000000000000000 1
b10100 8
1$
#1370000
0$
#1375000
b1000000000000000000 1
b10101 8
1$
#1380000
0$
#1385000
b10000000000000000 1
b10110 8
1$
#1390000
0$
#1395000
b100000000000000 1
b10111 8
1$
#1400000
0$
#1405000
b1000000000000 1
b11000 8
1$
#1410000
0$
#1415000
b10000000000 1
b11001 8
1$
#1420000
0$
#1425000
b100000000 1
b11010 8
1$
#1430000
0$
#1435000
b1000000 1
b11011 8
1$
#1440000
0$
#1445000
b10000 1
b11100 8
1$
#1450000
0$
#1455000
b100 1
b11101 8
1$
#1460000
0$
#1465000
b1 1
b11110 8
1$
#1470000
0$
#1475000
b1 2
b0 1
b1 3
b10 5
b11111 8
1$
#1480000
0$
#1485000
0#
1"
b100000 8
1$
#1490000
0$
#1495000
b100001 8
1$
#1500000
0$
#1505000
b10 6
b1001 -
b11 ,
b11111111111111111111111111111111 /
b10 +
b100 .
b100 7
1$
#1510000
0$
#1515000
1(
b100 %
b100 0
1$
#1520000
0$
#1525000
0(
1#
0"
b0 2
b100000000000000000000000000000000000000000000000000000000000000 1
b0 3
b100 5
b0 8
1$
#1530000
0$
#1535000
b1000000000000000000000000000000000000000000000000000000000000 1
b0 8
1$
#1540000
0$
#1545000
b10000000000000000000000000000000000000000000000000000000000 1
b1 8
1$
#1550000
0$
#1555000
b100000000000000000000000000000000000000000000000000000000 1
b10 8
1$
#1560000
0$
#1565000
b1000000000000000000000000000000000000000000000000000000 1
b11 8
1$
#1570000
0$
#1575000
b10000000000000000000000000000000000000000000000000000 1
b100 8
1$
#1580000
0$
#1585000
b100000000000000000000000000000000000000000000000000 1
b101 8
1$
#1590000
0$
#1595000
b1000000000000000000000000000000000000000000000000 1
b110 8
1$
#1600000
0$
#1605000
b10000000000000000000000000000000000000000000000 1
b111 8
1$
#1610000
0$
#1615000
b100000000000000000000000000000000000000000000 1
b1000 8
1$
#1620000
0$
#1625000
b1000000000000000000000000000000000000000000 1
b1001 8
1$
#1630000
0$
#1635000
b10000000000000000000000000000000000000000 1
b1010 8
1$
#1640000
0$
#1645000
b100000000000000000000000000000000000000 1
b1011 8
1$
#1650000
0$
#1655000
b1000000000000000000000000000000000000 1
b1100 8
1$
#1660000
0$
#1665000
b10000000000000000000000000000000000 1
b1101 8
1$
#1670000
0$
#1675000
b100000000000000000000000000000000 1
b1110 8
1$
#1680000
0$
#1685000
b1000000000000000000000000000000 1
b1111 8
1$
#1690000
0$
#1695000
b10000000000000000000000000000 1
b10000 8
1$
#1700000
0$
#1705000
b100000000000000000000000000 1
b10001 8
1$
#1710000
0$
#1715000
b1000000000000000000000000 1
b10010 8
1$
#1720000
0$
#1725000
b10000000000000000000000 1
b10011 8
1$
#1730000
0$
#1735000
b100000000000000000000 1
b10100 8
1$
#1740000
0$
#1745000
b1000000000000000000 1
b10101 8
1$
#1750000
0$
#1755000
b10000000000000000 1
b10110 8
1$
#1760000
0$
#1765000
b100000000000000 1
b10111 8
1$
#1770000
0$
#1775000
b1000000000000 1
b11000 8
1$
#1780000
0$
#1785000
b10000000000 1
b11001 8
1$
#1790000
0$
#1795000
b100000000 1
b11010 8
1$
#1800000
0$
#1805000
b1000000 1
b11011 8
1$
#1810000
0$
#1815000
b10000 1
b11100 8
1$
#1820000
0$
#1825000
b100 1
b11101 8
1$
#1830000
0$
#1835000
b1 2
b1 1
b100 3
b0 5
b11110 8
1$
#1840000
0$
#1845000
b10 2
b0 1
b10 3
b11111 8
1$
#1850000
0$
#1855000
0#
1"
b10 !
b10 4
b100000 8
1$
#1860000
0$
#1865000
b100001 8
1$
#1870000
0$
#1875000
b11 6
b1001 -
b11 ,
b11111111111111111111111111111111 /
b11 +
b1111 .
b1111 7
1$
#1880000
0$
#1885000
1(
b1111 %
b1111 0
1$
#1890000
0$
#1895000
0(
1#
0"
b0 2
b100000000000000000000000000000000000000000000000000000000000000 1
b0 3
b1111 5
b0 8
1$
#1900000
0$
#1905000
b1000000000000000000000000000000000000000000000000000000000000 1
b0 8
1$
#1910000
0$
#1915000
b10000000000000000000000000000000000000000000000000000000000 1
b1 8
1$
#1920000
0$
#1925000
b100000000000000000000000000000000000000000000000000000000 1
b10 8
1$
#1930000
0$
#1935000
b1000000000000000000000000000000000000000000000000000000 1
b11 8
1$
#1940000
0$
#1945000
b10000000000000000000000000000000000000000000000000000 1
b100 8
1$
#1950000
0$
#1955000
b100000000000000000000000000000000000000000000000000 1
b101 8
1$
#1960000
0$
#1965000
b1000000000000000000000000000000000000000000000000 1
b110 8
1$
#1970000
0$
#1975000
b10000000000000000000000000000000000000000000000 1
b111 8
1$
#1980000
0$
#1985000
b100000000000000000000000000000000000000000000 1
b1000 8
1$
#1990000
0$
#1995000
b1000000000000000000000000000000000000000000 1
b1001 8
1$
#2000000
0$
#2005000
b10000000000000000000000000000000000000000 1
b1010 8
1$
#2010000
0$
#2015000
b100000000000000000000000000000000000000 1
b1011 8
1$
#2020000
0$
#2025000
b1000000000000000000000000000000000000 1
b1100 8
1$
#2030000
0$
#2035000
b10000000000000000000000000000000000 1
b1101 8
1$
#2040000
0$
#2045000
b100000000000000000000000000000000 1
b1110 8
1$
#2050000
0$
#2055000
b1000000000000000000000000000000 1
b1111 8
1$
#2060000
0$
#2065000
b10000000000000000000000000000 1
b10000 8
1$
#2070000
0$
#2075000
b100000000000000000000000000 1
b10001 8
1$
#2080000
0$
#2085000
b1000000000000000000000000 1
b10010 8
1$
#2090000
0$
#2095000
b10000000000000000000000 1
b10011 8
1$
#2100000
0$
#2105000
b100000000000000000000 1
b10100 8
1$
#2110000
0$
#2115000
b1000000000000000000 1
b10101 8
1$
#2120000
0$
#2125000
b10000000000000000 1
b10110 8
1$
#2130000
0$
#2135000
b100000000000000 1
b10111 8
1$
#2140000
0$
#2145000
b1000000000000 1
b11000 8
1$
#2150000
0$
#2155000
b10000000000 1
b11001 8
1$
#2160000
0$
#2165000
b100000000 1
b11010 8
1$
#2170000
0$
#2175000
b1000000 1
b11011 8
1$
#2180000
0$
#2185000
b10000 1
b11100 8
1$
#2190000
0$
#2195000
b100 1
b11101 8
1$
#2200000
0$
#2205000
b1 2
b1 1
b100 3
b1011 5
b11110 8
1$
#2210000
0$
#2215000
b10 2
b0 1
b11 3
b110 5
b11111 8
1$
#2220000
0$
#2225000
0#
1"
b11 !
b11 4
b100000 8
1$
#2230000
0$
#2235000
b100001 8
1$
#2240000
0$
#2245000
b100 6
b11001 -
b101 ,
b11111111111111111111111111111111 /
b100 +
b10000 .
b10000 7
1$
#2250000
0$
#2255000
1(
b10000 %
b10000 0
1$
#2260000
0$
#2265000
0(
1#
0"
b0 2
b100000000000000000000000000000000000000000000000000000000000000 1
b0 3
b10000 5
b0 8
1$
#2270000
0$
#2275000
b1000000000000000000000000000000000000000000000000000000000000 1
b0 8
1$
#2280000
0$
#2285000
b10000000000000000000000000000000000000000000000000000000000 1
b1 8
1$
#2290000
0$
#2295000
b100000000000000000000000000000000000000000000000000000000 1
b10 8
1$
#2300000
0$
#2305000
b1000000000000000000000000000000000000000000000000000000 1
b11 8
1$
#2310000
0$
#2315000
b10000000000000000000000000000000000000000000000000000 1
b100 8
1$
#2320000
0$
#2325000
b100000000000000000000000000000000000000000000000000 1
b101 8
1$
#2330000
0$
#2335000
b1000000000000000000000000000000000000000000000000 1
b110 8
1$
#2340000
0$
#2345000
b10000000000000000000000000000000000000000000000 1
b111 8
1$
#2350000
0$
#2355000
b100000000000000000000000000000000000000000000 1
b1000 8
1$
#2360000
0$
#2365000
b1000000000000000000000000000000000000000000 1
b1001 8
1$
#2370000
0$
#2375000
b10000000000000000000000000000000000000000 1
b1010 8
1$
#2380000
0$
#2385000
b100000000000000000000000000000000000000 1
b1011 8
1$
#2390000
0$
#2395000
b1000000000000000000000000000000000000 1
b1100 8
1$
#2400000
0$
#2405000
b10000000000000000000000000000000000 1
b1101 8
1$
#2410000
0$
#2415000
b100000000000000000000000000000000 1
b1110 8
1$
#2420000
0$
#2425000
b1000000000000000000000000000000 1
b1111 8
1$
#2430000
0$
#2435000
b10000000000000000000000000000 1
b10000 8
1$
#2440000
0$
#2445000
b100000000000000000000000000 1
b10001 8
1$
#2450000
0$
#2455000
b1000000000000000000000000 1
b10010 8
1$
#2460000
0$
#2465000
b10000000000000000000000 1
b10011 8
1$
#2470000
0$
#2475000
b100000000000000000000 1
b10100 8
1$
#2480000
0$
#2485000
b1000000000000000000 1
b10101 8
1$
#2490000
0$
#2495000
b10000000000000000 1
b10110 8
1$
#2500000
0$
#2505000
b100000000000000 1
b10111 8
1$
#2510000
0$
#2515000
b1000000000000 1
b11000 8
1$
#2520000
0$
#2525000
b10000000000 1
b11001 8
1$
#2530000
0$
#2535000
b100000000 1
b11010 8
1$
#2540000
0$
#2545000
b1000000 1
b11011 8
1$
#2550000
0$
#2555000
b10000 1
b11100 8
1$
#2560000
0$
#2565000
b1 2
b100 1
b10000 3
b0 5
b11101 8
1$
#2570000
0$
#2575000
b10 2
b1 1
b1000 3
b11110 8
1$
#2580000
0$
#2585000
b11 2
b0 1
b100 3
b11111 8
1$
#2590000
0$
#2595000
0#
1"
b100 !
b100 4
b100000 8
1$
#2600000
0$
#2605000
b100001 8
1$
#2610000
0$
#2615000
b11001 -
b101 ,
b11111111111111111111111111111111 /
b100 +
b10001 .
b10001 7
1$
#2620000
0$
#2625000
1(
b10001 %
b10001 0
1$
#2630000
0$
#2635000
0(
1#
0"
b0 2
b100000000000000000000000000000000000000000000000000000000000000 1
b0 3
b10001 5
b0 8
1$
#2640000
0$
#2645000
b1000000000000000000000000000000000000000000000000000000000000 1
b0 8
1$
#2650000
0$
#2655000
b10000000000000000000000000000000000000000000000000000000000 1
b1 8
1$
#2660000
0$
#2665000
b100000000000000000000000000000000000000000000000000000000 1
b10 8
1$
#2670000
0$
#2675000
b1000000000000000000000000000000000000000000000000000000 1
b11 8
1$
#2680000
0$
#2685000
b10000000000000000000000000000000000000000000000000000 1
b100 8
1$
#2690000
0$
#2695000
b100000000000000000000000000000000000000000000000000 1
b101 8
1$
#2700000
0$
#2705000
b1000000000000000000000000000000000000000000000000 1
b110 8
1$
#2710000
0$
#2715000
b10000000000000000000000000000000000000000000000 1
b111 8
1$
#2720000
0$
#2725000
b100000000000000000000000000000000000000000000 1
b1000 8
1$
#2730000
0$
#2735000
b1000000000000000000000000000000000000000000 1
b1001 8
1$
#2740000
0$
#2745000
b10000000000000000000000000000000000000000 1
b1010 8
1$
#2750000
0$
#2755000
b100000000000000000000000000000000000000 1
b1011 8
1$
#2760000
0$
#2765000
b1000000000000000000000000000000000000 1
b1100 8
1$
#2770000
0$
#2775000
b10000000000000000000000000000000000 1
b1101 8
1$
#2780000
0$
#2785000
b100000000000000000000000000000000 1
b1110 8
1$
#2790000
0$
#2795000
b1000000000000000000000000000000 1
b1111 8
1$
#2800000
0$
#2805000
b10000000000000000000000000000 1
b10000 8
1$
#2810000
0$
#2815000
b100000000000000000000000000 1
b10001 8
1$
#2820000
0$
#2825000
b1000000000000000000000000 1
b10010 8
1$
#2830000
0$
#2835000
b10000000000000000000000 1
b10011 8
1$
#2840000
0$
#2845000
b100000000000000000000 1
b10100 8
1$
#2850000
0$
#2855000
b1000000000000000000 1
b10101 8
1$
#2860000
0$
#2865000
b10000000000000000 1
b10110 8
1$
#2870000
0$
#2875000
b100000000000000 1
b10111 8
1$
#2880000
0$
#2885000
b1000000000000 1
b11000 8
1$
#2890000
0$
#2895000
b10000000000 1
b11001 8
1$
#2900000
0$
#2905000
b100000000 1
b11010 8
1$
#2910000
0$
#2915000
b1000000 1
b11011 8
1$
#2920000
0$
#2925000
b10000 1
b11100 8
1$
#2930000
0$
#2935000
b1 2
b100 1
b10000 3
b1 5
b11101 8
1$
#2940000
0$
#2945000
b10 2
b1 1
b1000 3
b11110 8
1$
#2950000
0$
#2955000
b11 2
b0 1
b100 3
b11111 8
1$
#2960000
0$
#2965000
0#
1"
b100000 8
1$
#2970000
0$
#2975000
b100001 8
1$
#2980000
0$
#2985000
b11001 -
b101 ,
b11111111111111111111111111111111 /
b100 +
b11000 .
b11000 7
1$
#2990000
0$
#2995000
1(
b11000 %
b11000 0
1$
#3000000
0$
#3005000
0(
1#
0"
b0 2
b100000000000000000000000000000000000000000000000000000000000000 1
b0 3
b11000 5
b0 8
1$
#3010000
0$
#3015000
b1000000000000000000000000000000000000000000000000000000000000 1
b0 8
1$
#3020000
0$
#3025000
b10000000000000000000000000000000000000000000000000000000000 1
b1 8
1$
#3030000
0$
#3035000
b100000000000000000000000000000000000000000000000000000000 1
b10 8
1$
#3040000
0$
#3045000
b1000000000000000000000000000000000000000000000000000000 1
b11 8
1$
#3050000
0$
#3055000
b10000000000000000000000000000000000000000000000000000 1
b100 8
1$
#3060000
0$
#3065000
b100000000000000000000000000000000000000000000000000 1
b101 8
1$
#3070000
0$
#3075000
b1000000000000000000000000000000000000000000000000 1
b110 8
1$
#3080000
0$
#3085000
b10000000000000000000000000000000000000000000000 1
b111 8
1$
#3090000
0$
#3095000
b100000000000000000000000000000000000000000000 1
b1000 8
1$
#3100000
0$
#3105000
b1000000000000000000000000000000000000000000 1
b1001 8
1$
#3110000
0$
#3115000
b10000000000000000000000000000000000000000 1
b1010 8
1$
#3120000
0$
#3125000
b100000000000000000000000000000000000000 1
b1011 8
1$
#3130000
0$
#3135000
b1000000000000000000000000000000000000 1
b1100 8
1$
#3140000
0$
#3145000
b10000000000000000000000000000000000 1
b1101 8
1$
#3150000
0$
#3155000
b100000000000000000000000000000000 1
b1110 8
1$
#3160000
0$
#3165000
b1000000000000000000000000000000 1
b1111 8
1$
#3170000
0$
#3175000
b10000000000000000000000000000 1
b10000 8
1$
#3180000
0$
#3185000
b100000000000000000000000000 1
b10001 8
1$
#3190000
0$
#3195000
b1000000000000000000000000 1
b10010 8
1$
#3200000
0$
#3205000
b10000000000000000000000 1
b10011 8
1$
#3210000
0$
#3215000
b100000000000000000000 1
b10100 8
1$
#3220000
0$
#3225000
b1000000000000000000 1
b10101 8
1$
#3230000
0$
#3235000
b10000000000000000 1
b10110 8
1$
#3240000
0$
#3245000
b100000000000000 1
b10111 8
1$
#3250000
0$
#3255000
b1000000000000 1
b11000 8
1$
#3260000
0$
#3265000
b10000000000 1
b11001 8
1$
#3270000
0$
#3275000
b100000000 1
b11010 8
1$
#3280000
0$
