Verilog Library/src/divide_u64.v
`timescale 1ns/1ps

module divide_u64 (
    input  wire        clk,
    input  wire        rst,
    input  wire        start,
    input  wire [63:0] numerator,
    input  wire [63:0] denominator,
    output reg  [63:0] quotient,
    output reg  [63:0] remainder,
    output reg         busy,
    output reg         done,
    output reg         div_by_zero
);

    reg [63:0] numerator_reg;
    reg [63:0] denominator_reg;
    reg [63:0] quotient_work;
    reg [64:0] remainder_work;
    reg [6:0]  bit_index;

    reg [64:0] rem_shifted;
    reg [64:0] rem_next;
    reg [63:0] q_next;

    always @(posedge clk) begin
        if (rst) begin
            numerator_reg   <= 64'd0;
            denominator_reg <= 64'd0;
            quotient_work   <= 64'd0;
            remainder_work  <= 65'd0;
            bit_index       <= 7'd0;
            quotient        <= 64'd0;
            remainder       <= 64'd0;
            busy            <= 1'b0;
            done            <= 1'b0;
            div_by_zero     <= 1'b0;
            rem_shifted     <= 65'd0;
            rem_next        <= 65'd0;
            q_next          <= 64'd0;
        end else begin
            if (start && !busy) begin
                done <= 1'b0;
                if (denominator == 64'd0) begin
                    quotient        <= 64'd0;
                    remainder       <= numerator;
                    busy            <= 1'b0;
                    done            <= 1'b1;
                    div_by_zero     <= 1'b1;
                end else begin
                    numerator_reg   <= numerator;
                    denominator_reg <= denominator;
                    quotient_work   <= 64'd0;
                    remainder_work  <= 65'd0;
                    bit_index       <= 7'd63;
                    busy            <= 1'b1;
                    done            <= 1'b0;
                    div_by_zero     <= 1'b0;
                end
            end else if (busy) begin
                rem_shifted = {remainder_work[63:0], numerator_reg[bit_index]};
                q_next = quotient_work;

                if (rem_shifted >= {1'b0, denominator_reg}) begin
                    rem_next = rem_shifted - {1'b0, denominator_reg};
                    q_next[bit_index] = 1'b1;
                end else begin
                    rem_next = rem_shifted;
                end

                remainder_work <= rem_next;
                quotient_work  <= q_next;

                if (bit_index == 7'd0) begin
                    quotient    <= q_next;
                    remainder   <= rem_next[63:0];
                    busy        <= 1'b0;
                    done        <= 1'b1;
                end else begin
                    bit_index <= bit_index - 1'b1;
                end
            end
        end
    end

endmodule

Verilog Testing/tb/divide_u64_tb.v
`timescale 1ns/1ps
`define START_TIMEOUT_CYCLES 50
`define DONE_TIMEOUT_CYCLES  500

module divide_u64_tb;
    reg         clk;
    reg         rst;
    reg         start;
    reg  [63:0] numerator;
    reg  [63:0] denominator;
    wire [63:0] quotient;
    wire [63:0] remainder;
    wire        busy;
    wire        done;
    wire        div_by_zero;

    integer     errors;

    divide_u64 dut (
        .clk(clk),
        .rst(rst),
        .start(start),
        .numerator(numerator),
        .denominator(denominator),
        .quotient(quotient),
        .remainder(remainder),
        .busy(busy),
        .done(done),
        .div_by_zero(div_by_zero)
    );

    always #5 clk = ~clk;

    task run_case;
        input [63:0] num_i;
        input [63:0] den_i;
        reg   [63:0] exp_q;
        reg   [63:0] exp_r;
        integer timeout;
        begin
            if (den_i == 64'd0) begin
                exp_q = 64'd0;
                exp_r = num_i;
            end else begin
                exp_q = num_i / den_i;
                exp_r = num_i % den_i;
            end

            @(posedge clk);
            numerator   <= num_i;
            denominator <= den_i;
            start       <= 1'b1;
            @(posedge clk);
            start       <= 1'b0;
            @(posedge clk);

            timeout = 0;
            while (!busy && !done && timeout < `START_TIMEOUT_CYCLES) begin
                @(posedge clk);
                timeout = timeout + 1;
            end

            timeout = 0;
            while ((busy || !done) && timeout < `DONE_TIMEOUT_CYCLES) begin
                @(posedge clk);
                timeout = timeout + 1;
            end

            if (busy || !done) begin
                $display("TIMEOUT: num=%0d den=%0d", num_i, den_i);
                errors = errors + 1;
            end else if (den_i == 64'd0) begin
                if (!div_by_zero || quotient !== exp_q || remainder !== exp_r) begin
                    $display("FAIL(DBZ): num=%0d den=%0d q=%0d r=%0d dbz=%0b", num_i, den_i, quotient, remainder, div_by_zero);
                    errors = errors + 1;
                end else begin
                    $display("PASS(DBZ): num=%0d den=%0d q=%0d r=%0d", num_i, den_i, quotient, remainder);
                end
            end else if (div_by_zero || quotient !== exp_q || remainder !== exp_r) begin
                $display(
                    "FAIL: num=%0d den=%0d exp_q=%0d got_q=%0d exp_r=%0d got_r=%0d dbz=%0b",
                    num_i, den_i, exp_q, quotient, exp_r, remainder, div_by_zero
                );
                errors = errors + 1;
            end else begin
                $display("PASS: num=%0d den=%0d q=%0d r=%0d cycles=%0d", num_i, den_i, quotient, remainder, timeout);
            end

            @(posedge clk);
        end
    endtask

    integer n;
    reg [63:0] rnd_num;
    reg [63:0] rnd_den;

    initial begin
        $dumpfile("outputs/divide_u64_tb.vcd");
        $dumpvars(0, divide_u64_tb);

        clk         = 1'b0;
        rst         = 1'b1;
        start       = 1'b0;
        numerator   = 64'd0;
        denominator = 64'd0;
        errors      = 0;

        repeat (3) @(posedge clk);
        rst = 1'b0;

        run_case(64'd0, 64'd1);
        run_case(64'd1, 64'd1);
        run_case(64'd2, 64'd1);
        run_case(64'd7, 64'd3);
        run_case(64'd1000, 64'd7);
        run_case(64'hFFFF_FFFF_FFFF_FFFF, 64'd1);
        run_case(64'hFFFF_FFFF_FFFF_FFFF, 64'd2);
        run_case(64'hFFFF_FFFF_FFFF_FFFF, 64'hFFFF_FFFF);
        run_case(64'h1234_5678_9ABC_DEF0, 64'h1111_1111);
        run_case(64'h7FFF_FFFF_FFFF_FFFF, 64'd123456789);
        run_case(64'd123, 64'd0);

        for (n = 0; n < 20; n = n + 1) begin
            rnd_num = {$random, $random};
            rnd_den = {$random, $random};
            if (rnd_den == 64'd0) begin
                rnd_den = 64'd1;
            end
            run_case(rnd_num, rnd_den);
        end

        if (errors == 0) begin
            $display("ALL TESTS PASSED");
        end else begin
            $display("TESTS FAILED: %0d errors", errors);
        end

        $finish;
    end
endmodule

Verilog Library/outputs/divide_u64_tb.vcd
$date
	Wed Feb 25 17:42:44 2026
$end
$version
	Icarus Verilog
$end
$timescale
	1ps
$end
$scope module divide_u64_tb $end
$var wire 64 ! remainder [63:0] $end
$var wire 64 " quotient [63:0] $end
$var wire 1 # done $end
$var wire 1 $ div_by_zero $end
$var wire 1 % busy $end
$var reg 1 & clk $end
$var reg 64 ' denominator [63:0] $end
$var reg 64 ( numerator [63:0] $end
$var reg 64 ) rnd_den [63:0] $end
$var reg 64 * rnd_num [63:0] $end
$var reg 1 + rst $end
$var reg 1 , start $end
$var integer 32 - errors [31:0] $end
$var integer 32 . n [31:0] $end
$scope module dut $end
$var wire 1 & clk $end
$var wire 64 / denominator [63:0] $end
$var wire 64 0 numerator [63:0] $end
$var wire 1 + rst $end
$var wire 1 , start $end
$var reg 7 1 bit_index [6:0] $end
$var reg 1 % busy $end
$var reg 64 2 denominator_reg [63:0] $end
$var reg 1 $ div_by_zero $end
$var reg 1 # done $end
$var reg 64 3 numerator_reg [63:0] $end
$var reg 64 4 q_next [63:0] $end
$var reg 64 5 quotient [63:0] $end
$var reg 64 6 quotient_work [63:0] $end
$var reg 65 7 rem_next [64:0] $end
$var reg 65 8 rem_shifted [64:0] $end
$var reg 64 9 remainder [63:0] $end
$var reg 65 : remainder_work [64:0] $end
$upscope $end
$scope task run_case $end
$var reg 64 ; den_i [63:0] $end
$var reg 64 < exp_q [63:0] $end
$var reg 64 = exp_r [63:0] $end
$var reg 64 > num_i [63:0] $end
$var integer 32 ? timeout [31:0] $end
$upscope $end
$upscope $end
$enddefinitions $end
$comment Show the parameter values. $end
$dumpall
$end
#0
$dumpvars
bx ?
bx >
bx =
bx <
bx ;
bx :
bx 9
bx 8
bx 7
bx 6
bx 5
bx 4
bx 3
bx 2
bx 1
b0 0
b0 /
bx .
b0 -
0,
1+
bx *
bx )
b0 (
b0 '
0&
x%
x$
x#
bx "
bx !
$end
#5000
b0 4
b0 7
b0 8
0$
0#
0%
b0 !
b0 9
b0 "
b0 5
b0 1
b0 :
b0 6
b0 2
b0 3
1&
#10000
0&
#15000
1&
#20000
0&
#25000
b0 =
b0 <
b1 ;
b0 >
0+
1&
#30000
0&
#35000
1,
b1 '
b1 /
1&
#40000
0&
#45000
0,
1%
b111111 1
b1 2
1&
#50000
0&
#55000
b111110 1
b0 ?
1&
#60000
0&
#65000
b111101 1
b1 ?
1&
#70000
0&
#75000
b111100 1
b10 ?
1&
#80000
0&
#85000
b111011 1
b11 ?
1&
#90000
0&
#95000
b111010 1
b100 ?
1&
#100000
0&
#105000
b111001 1
b101 ?
1&
#110000
0&
#115000
b111000 1
b110 ?
1&
#120000
0&
#125000
b110111 1
b111 ?
1&
#130000
0&
#135000
b110110 1
b1000 ?
1&
#140000
0&
#145000
b110101 1
b1001 ?
1&
#150000
0&
#155000
b110100 1
b1010 ?
1&
#160000
0&
#165000
b110011 1
b1011 ?
1&
#170000
0&
#175000
b110010 1
b1100 ?
1&
#180000
0&
#185000
b110001 1
b1101 ?
1&
#190000
0&
#195000
b110000 1
b1110 ?
1&
#200000
0&
#205000
b101111 1
b1111 ?
1&
#210000
0&
#215000
b101110 1
b10000 ?
1&
#220000
0&
#225000
b101101 1
b10001 ?
1&
#230000
0&
#235000
b101100 1
b10010 ?
1&
#240000
0&
#245000
b101011 1
b10011 ?
1&
#250000
0&
#255000
b101010 1
b10100 ?
1&
#260000
0&
#265000
b101001 1
b10101 ?
1&
#270000
0&
#275000
b101000 1
b10110 ?
1&
#280000
0&
#285000
b100111 1
b10111 ?
1&
#290000
0&
#295000
b100110 1
b11000 ?
1&
#300000
0&
#305000
b100101 1
b11001 ?
1&
#310000
0&
#315000
b100100 1
b11010 ?
1&
#320000
0&
#325000
b100011 1
b11011 ?
1&
#330000
0&
#335000
b100010 1
b11100 ?
1&
#340000
0&
#345000
b100001 1
b11101 ?
1&
#350000
0&
#355000
b100000 1
b11110 ?
1&
#360000
0&
#365000
b11111 1
b11111 ?
1&
#370000
0&
#375000
b11110 1
b100000 ?
1&
#380000
0&
#385000
b11101 1
b100001 ?
1&
#390000
0&
#395000
b11100 1
b100010 ?
1&
#400000
0&
#405000
b11011 1
b100011 ?
1&
#410000
0&
#415000
b11010 1
b100100 ?
1&
#420000
0&
#425000
b11001 1
b100101 ?
1&
#430000
0&
#435000
b11000 1
b100110 ?
1&
#440000
0&
#445000
b10111 1
b100111 ?
1&
#450000
0&
#455000
b10110 1
b101000 ?
1&
#460000
0&
#465000
b10101 1
b101001 ?
1&
#470000
0&
#475000
b10100 1
b101010 ?
1&
#480000
0&
#485000
b10011 1
b101011 ?
1&
#490000
0&
#495000
b10010 1
b101100 ?
1&
#500000
0&
#505000
b10001 1
b101101 ?
1&
#510000
0&
#515000
b10000 1
b101110 ?
1&
#520000
0&
#525000
b1111 1
b101111 ?
1&
#530000
0&
#535000
b1110 1
b110000 ?
1&
#540000
0&
#545000
b1101 1
b110001 ?
1&
#550000
0&
#555000
b1100 1
b110010 ?
1&
#560000
0&
#565000
b1011 1
b110011 ?
1&
#570000
0&
#575000
b1010 1
b110100 ?
1&
#580000
0&
#585000
b1001 1
b110101 ?
1&
#590000
0&
#595000
b1000 1
b110110 ?
1&
#600000
0&
#605000
b111 1
b110111 ?
1&
#610000
0&
#615000
b110 1
b111000 ?
1&
#620000
0&
#625000
b101 1
b111001 ?
1&
#630000
0&
#635000
b100 1
b111010 ?
1&
#640000
0&
#645000
b11 1
b111011 ?
1&
#650000
0&
#655000
b10 1
b111100 ?
1&
#660000
0&
#665000
b1 1
b111101 ?
1&
#670000
0&
#675000
b0 1
b111110 ?
1&
#680000
0&
#685000
1#
0%
b111111 ?
1&
#690000
0&
#695000
b1000000 ?
1&
#700000
0&
#705000
b1 <
b1 >
1&
#710000
0&
#715000
1,
b1 (
b1 0
1&
#720000
0&
#725000
0,
1%
b111111 1
b1 3
0#
1&
#730000
0&
#735000
b111110 1
b0 ?
1&
#740000
0&
#745000
b111101 1
b1 ?
1&
#750000
0&
#755000
b111100 1
b10 ?
1&
#760000
0&
#765000
b111011 1
b11 ?
1&
#770000
0&
#775000
b111010 1
b100 ?
1&
#780000
0&
#785000
b111001 1
b101 ?
1&
#790000
0&
#795000
b111000 1
b110 ?
1&
#800000
0&
#805000
b110111 1
b111 ?
1&
#810000
0&
#815000
b110110 1
b1000 ?
1&
#820000
0&
#825000
b110101 1
b1001 ?
1&
#830000
0&
#835000
b110100 1
b1010 ?
1&
#840000
0&
#845000
b110011 1
b1011 ?
1&
#850000
0&
#855000
b110010 1
b1100 ?
1&
#860000
0&
#865000
b110001 1
b1101 ?
1&
#870000
0&
#875000
b110000 1
b1110 ?
1&
#880000
0&
#885000
b101111 1
b1111 ?
1&
#890000
0&
#895000
b101110 1
b10000 ?
1&
#900000
0&
#905000
b101101 1
b10001 ?
1&
#910000
0&
#915000
b101100 1
b10010 ?
1&
#920000
0&
#925000
b101011 1
b10011 ?
1&
#930000
0&
#935000
b101010 1
b10100 ?
1&
#940000
0&
#945000
b101001 1
b10101 ?
1&
#950000
0&
#955000
b101000 1
b10110 ?
1&
#960000
0&
#965000
b100111 1
b10111 ?
1&
#970000
0&
#975000
b100110 1
b11000 ?
1&
#980000
0&
#985000
b100101 1
b11001 ?
1&
#990000
0&
#995000
b100100 1
b11010 ?
1&
#1000000
0&
#1005000
b100011 1
b11011 ?
1&
#1010000
0&
#1015000
b100010 1
b11100 ?
1&
#1020000
0&
#1025000
b100001 1
b11101 ?
1&
#1030000
0&
#1035000
b100000 1
b11110 ?
1&
#1040000
0&
#1045000
b11111 1
b11111 ?
1&
#1050000
0&
#1055000
b11110 1
b100000 ?
1&
#1060000
0&
#1065000
b11101 1
b100001 ?
1&
#1070000
0&
#1075000
b11100 1
b100010 ?
1&
#1080000
0&
#1085000
b11011 1
b100011 ?
1&
#1090000
0&
#1095000
b11010 1
b100100 ?
1&
#1100000
0&
#1105000
b11001 1
b100101 ?
1&
#1110000
0&
#1115000
b11000 1
b100110 ?
1&
#1120000
0&
#1125000
b10111 1
b100111 ?
1&
#1130000
0&
#1135000
b10110 1
b101000 ?
1&
#1140000
0&
#1145000
b10101 1
b101001 ?
1&
#1150000
0&
#1155000
b10100 1
b101010 ?
1&
#1160000
0&
#1165000
b10011 1
b101011 ?
1&
#1170000
0&
#1175000
b10010 1
b101100 ?
1&
#1180000
0&
#1185000
b10001 1
b101101 ?
1&
#1190000
0&
#1195000
b10000 1
b101110 ?
1&
#1200000
0&
#1205000
b1111 1
b101111 ?
1&
#1210000
0&
#1215000
b1110 1
b110000 ?
1&
#1220000
0&
#1225000
b1101 1
b110001 ?
1&
#1230000
0&
#1235000
b1100 1
b110010 ?
1&
#1240000
0&
#1245000
b1011 1
b110011 ?
1&
#1250000
0&
#1255000
b1010 1
b110100 ?
1&
#1260000
0&
#1265000
b1001 1
b110101 ?
1&
#1270000
0&
#1275000
b1000 1
b110110 ?
1&
#1280000
0&
#1285000
b111 1
b110111 ?
1&
#1290000
0&
#1295000
b110 1
b111000 ?
1&
#1300000
0&
#1305000
b101 1
b111001 ?
1&
#1310000
0&
#1315000
b100 1
b111010 ?
1&
#1320000
0&
#1325000
b11 1
b111011 ?
1&
#1330000
0&
#1335000
b10 1
b111100 ?
1&
#1340000
0&
#1345000
b1 1
b111101 ?
1&
#1350000
0&
#1355000
b0 1
b111110 ?
1&
#1360000
0&
#1365000
1#
0%
b1 "
b1 5
b1 6
b111111 ?
b1 4
b1 8
1&
#1370000
0&
#1375000
b1000000 ?
1&
#1380000
0&
#1385000
b10 <
b10 >
1&
#1390000
0&
#1395000
1,
b10 (
b10 0
1&
#1400000
0&
#1405000
0,
1%
b111111 1
b0 6
b10 3
0#
1&
#1410000
0&
#1415000
b111110 1
b0 4
b0 8
b0 ?
1&
#1420000
0&
#1425000
b111101 1
b1 ?
1&
#1430000
0&
#1435000
b111100 1
b10 ?
1&
#1440000
0&
#1445000
b111011 1
b11 ?
1&
#1450000
0&
#1455000
b111010 1
b100 ?
1&
#1460000
0&
#1465000
b111001 1
b101 ?
1&
#1470000
0&
#1475000
b111000 1
b110 ?
1&
#1480000
0&
#1485000
b110111 1
b111 ?
1&
#1490000
0&
#1495000
b110110 1
b1000 ?
1&
#1500000
0&
#1505000
b110101 1
b1001 ?
1&
#1510000
0&
#1515000
b110100 1
b1010 ?
1&
#1520000
0&
#1525000
b110011 1
b1011 ?
1&
#1530000
0&
#1535000
b110010 1
b1100 ?
1&
#1540000
0&
#1545000
b110001 1
b1101 ?
1&
#1550000
0&
#1555000
b110000 1
b1110 ?
1&
#1560000
0&
#1565000
b101111 1
b1111 ?
1&
#1570000
0&
#1575000
b101110 1
b10000 ?
1&
#1580000
0&
#1585000
b101101 1
b10001 ?
1&
#1590000
0&
#1595000
b101100 1
b10010 ?
1&
#1600000
0&
#1605000
b101011 1
b10011 ?
1&
#1610000
0&
#1615000
b101010 1
b10100 ?
1&
#1620000
0&
#1625000
b101001 1
b10101 ?
1&
#1630000
0&
#1635000
b101000 1
b10110 ?
1&
#1640000
0&
#1645000
b100111 1
b10111 ?
1&
#1650000
0&
#1655000
b100110 1
b11000 ?
1&
#1660000
0&
#1665000
b100101 1
b11001 ?
1&
#1670000
0&
#1675000
b100100 1
b11010 ?
1&
#1680000
0&
#1685000
b100011 1
b11011 ?
1&
#1690000
0&
#1695000
b100010 1
b11100 ?
1&
#1700000
0&
#1705000
b100001 1
b11101 ?
1&
#1710000
0&
#1715000
b100000 1
b11110 ?
1&
#1720000
0&
#1725000
b11111 1
b11111 ?
1&
#1730000
0&
#1735000
b11110 1
b100000 ?
1&
#1740000
0&
#1745000
b11101 1
b100001 ?
1&
#1750000
0&
#1755000
b11100 1
b100010 ?
1&
#1760000
0&
#1765000
b11011 1
b100011 ?
1&
#1770000
0&
#1775000
b11010 1
b100100 ?
1&
#1780000
0&
#1785000
b11001 1
b100101 ?
1&
#1790000
0&
#1795000
b11000 1
b100110 ?
1&
#1800000
0&
#1805000
b10111 1
b100111 ?
1&
#1810000
0&
#1815000
b10110 1
b101000 ?
1&
#1820000
0&
#1825000
b10101 1
b101001 ?
1&
#1830000
0&
#1835000
b10100 1
b101010 ?
1&
#1840000
0&
#1845000
b10011 1
b101011 ?
1&
#1850000
0&
#1855000
b10010 1
b101100 ?
1&
#1860000
0&
#1865000
b10001 1
b101101 ?
1&
#1870000
0&
#1875000
b10000 1
b101110 ?
1&
#1880000
0&
#1885000
b1111 1
b101111 ?
1&
#1890000
0&
#1895000
b1110 1
b110000 ?
1&
#1900000
0&
#1905000
b1101 1
b110001 ?
1&
#1910000
0&
#1915000
b1100 1
b110010 ?
1&
#1920000
0&
#1925000
b1011 1
b110011 ?
1&
#1930000
0&
#1935000
b1010 1
b110100 ?
1&
#1940000
0&
#1945000
b1001 1
b110101 ?
1&
#1950000
0&
#1955000
b1000 1
b110110 ?
1&
#1960000
0&
#1965000
b111 1
b110111 ?
1&
#1970000
0&
#1975000
b110 1
b111000 ?
1&
#1980000
0&
#1985000
b101 1
b111001 ?
1&
#1990000
0&
#1995000
b100 1
b111010 ?
1&
#2000000
0&
#2005000
b11 1
b111011 ?
1&
#2010000
0&
#2015000
b10 1
b111100 ?
1&
#2020000
0&
#2025000
b1 1
b111101 ?
1&
#2030000
0&
#2035000
b0 1
b10 6
b10 4
b1 8
b111110 ?
1&
#2040000
0&
#2045000
1#
0%
b10 "
b10 5
b111111 ?
b0 8
1&
#2050000
0&
#2055000
b1000000 ?
1&
#2060000
0&
#2065000
b1 =
b11 ;
b111 >
1&
#2070000
0&
#2075000
1,
b11 '
b11 /
b111 (
b111 0
1&
#2080000
0&
#2085000
0,
1%
b111111 1
b0 6
b11 2
b111 3
0#
1&
#2090000
0&
#2095000
b111110 1
b0 4
b0 ?
1&
#2100000
0&
#2105000
b111101 1
b1 ?
1&
#2110000
0&
#2115000
b111100 1
b10 ?
1&
#2120000
0&
#2125000
b111011 1
b11 ?
1&
#2130000
0&
#2135000
b111010 1
b100 ?
1&
#2140000
0&
#2145000
b111001 1
b101 ?
1&
#2150000
0&
#2155000
b111000 1
b110 ?
1&
#2160000
0&
#2165000
b110111 1
b111 ?
1&
#2170000
0&
#2175000
b110110 1
b1000 ?
1&
#2180000
0&
#2185000
b110101 1
b1001 ?
1&
#2190000
0&
#2195000
b110100 1
b1010 ?
1&
#2200000
0&
#2205000
b110011 1
b1011 ?
1&
#2210000
0&
#2215000
b110010 1
b1100 ?
1&
#2220000
0&
#2225000
b110001 1
b1101 ?
1&
#2230000
0&
#2235000
b110000 1
b1110 ?
1&
#2240000
0&
#2245000
b101111 1
b1111 ?
1&
#2250000
0&
#2255000
b101110 1
b10000 ?
1&
#2260000
0&
#2265000
b101101 1
b10001 ?
1&
#2270000
0&
#2275000
b101100 1
b10010 ?
1&
#2280000
0&
#2285000
b101011 1
b10011 ?
1&
#2290000
0&
#2295000
b101010 1
b10100 ?
1&
#2300000
0&
#2305000
b101001 1
b10101 ?
1&
#2310000
0&
#2315000
b101000 1
b10110 ?
1&
#2320000
0&
#2325000
b100111 1
b10111 ?
1&
#2330000
0&
#2335000
b100110 1
b11000 ?
1&
#2340000
0&
#2345000
b100101 1
b11001 ?
1&
#2350000
0&
#2355000
b100100 1
b11010 ?
1&
#2360000
0&
#2365000
b100011 1
b11011 ?
1&
#2370000
0&
#2375000
b100010 1
b11100 ?
1&
#2380000
0&
#2385000
b100001 1
b11101 ?
1&
#2390000
0&
#2395000
b100000 1
b11110 ?
1&
#2400000
0&
#2405000
b11111 1
b11111 ?
1&
#2410000
0&
#2415000
b11110 1
b100000 ?
1&
#2420000
0&
#2425000
b11101 1
b100001 ?
1&
#2430000
0&
#2435000
b11100 1
b100010 ?
1&
#2440000
0&
#2445000
b11011 1
b100011 ?
1&
#2450000
0&
#2455000
b11010 1
b100100 ?
1&
#2460000
0&
#2465000
b11001 1
b100101 ?
1&
#2470000
0&
#2475000
b11000 1
b100110 ?
1&
#2480000
0&
#2485000
b10111 1
b100111 ?
1&
#2490000
0&
#2495000
b10110 1
b101000 ?
1&
#2500000
0&
#2505000
b10101 1
b101001 ?
1&
#2510000
0&
#2515000
b10100 1
b101010 ?
1&
#2520000
0&
#2525000
b10011 1
b101011 ?
1&
#2530000
0&
#2535000
b10010 1
b101100 ?
1&
#2540000
0&
#2545000
b10001 1
b101101 ?
1&
#2550000
0&
#2555000
b10000 1
b101110 ?
1&
#2560000
0&
#2565000
b1111 1
b101111 ?
1&
#2570000
0&
#2575000
b1110 1
b110000 ?
1&
#2580000
0&
#2585000
b1101 1
b110001 ?
1&
#2590000
0&
#2595000
b1100 1
b110010 ?
1&
#2600000
0&
#2605000
b1011 1
b110011 ?
1&
#2610000
0&
#2615000
b1010 1
b110100 ?
1&
#2620000
0&
#2625000
b1001 1
b110101 ?
1&
#2630000
0&
#2635000
b1000 1
b110110 ?
1&
#2640000
0&
#2645000
b111 1
b110111 ?
1&
#2650000
0&
#2655000
b110 1
b111000 ?
1&
#2660000
0&
#2665000
b101 1
b111001 ?
1&
#2670000
0&
#2675000
b100 1
b111010 ?
1&
#2680000
0&
#2685000
b11 1
b111011 ?
1&
#2690000
0&
#2695000
b10 1
b111100 ?
1&
#2700000
0&
#2705000
b1 1
b1 :
b111101 ?
b1 7
b1 8
1&
#2710000
0&
#2715000
b0 1
b10 6
b0 :
b10 4
b0 7
b11 8
b111110 ?
1&
#2720000
0&
#2725000
1#
0%
b1 !
b1 9
b1 :
b111111 ?
b1 7
b1 8
1&
#2730000
0&
#2735000
b1000000 ?
1&
#2740000
0&
#2745000
b110 =
b10001110 <
b111 ;
b1111101000 >
1&
#2750000
0&
#2755000
1,
b111 '
b111 /
b1111101000 (
b1111101000 0
1&
#2760000
0&
#2765000
0,
1%
b111111 1
b0 :
b0 6
b111 2
b1111101000 3
0#
1&
#2770000
0&
#2775000
b111110 1
b0 7
b0 4
b0 8
b0 ?
1&
#2780000
0&
#2785000
b111101 1
b1 ?
1&
#2790000
0&
#2795000
b111100 1
b10 ?
1&
#2800000
0&
#2805000
b111011 1
b11 ?
1&
#2810000
0&
#2815000
b111010 1
b100 ?
1&
#2820000
0&
#2825000
b111001 1
b101 ?
1&
#2830000
0&
#2835000
b111000 1
b110 ?
1&
#2840000
0&
#2845000
b110111 1
b111 ?
1&
#2850000
0&
#2855000
b110110 1
b1000 ?
1&
#2860000
0&
#2865000
b110101 1
b1001 ?
1&
#2870000
0&
#2875000
b110100 1
b1010 ?
1&
#2880000
0&
#2885000
b110011 1
b1011 ?
1&
#2890000
0&
#2895000
b110010 1
b1100 ?
1&
#2900000
0&
#2905000
b110001 1
b1101 ?
1&
#2910000
0&
#2915000
b110000 1
b1110 ?
1&
#2920000
0&
#2925000
b101111 1
b1111 ?
1&
#2930000
0&
#2935000
b101110 1
b10000 ?
1&
#2940000
0&
#2945000
b101101 1
b10001 ?
1&
#2950000
0&
#2955000
b101100 1
b10010 ?
1&
#2960000
0&
#2965000
b101011 1
b10011 ?
1&
#2970000
0&
#2975000
b101010 1
b10100 ?
1&
#2980000
0&
#2985000
b101001 1
b10101 ?
1&
#2990000
0&
#2995000
b101000 1
b10110 ?
1&
#3000000
0&
#3005000
b100111 1
b10111 ?
1&
#3010000
0&
#3015000
b100110 1
b11000 ?
1&
#3020000
0&
#3025000
b100101 1
b11001 ?
1&
#3030000
0&
#3035000
b100100 1
b11010 ?
1&
#3040000
0&
#3045000
b100011 1
b11011 ?
1&
#3050000
0&
#3055000
b100010 1
b11100 ?
1&
#3060000
0&
#3065000
b100001 1
b11101 ?
1&
#3070000
0&
#3075000
b100000 1
b11110 ?
1&
#3080000
0&
#3085000
b11111 1
b11111 ?
1&
#3090000
0&
#3095000
b11110 1
b100000 ?
1&
#3100000
0&
#3105000
b11101 1
b100001 ?
1&
#3110000
0&
#3115000
b11100 1
b100010 ?
1&
#3120000
0&
#3125000
b11011 1
b100011 ?
1&
#3130000
0&
#3135000
b11010 1
b100100 ?
1&
#3140000
0&
#3145000
b11001 1
b100101 ?
1&
#3150000
0&
#3155000
b11000 1
b100110 ?
1&
#3160000
0&
#3165000
b10111 1
b100111 ?
1&
#3170000
0&
#3175000
b10110 1
b101000 ?
1&
#3180000
0&
#3185000
b10101 1
b101001 ?
1&
#3190000
0&
#3195000
b10100 1
b101010 ?
1&
#3200000
0&
#3205000
b10011 1
b101011 ?
1&
#3210000
0&
#3215000
b10010 1
b101100 ?
1&
#3220000
0&
#3225000
b10001 1
b101101 ?
1&
#3230000
0&
#3235000
b10000 1
b101110 ?
1&
#3240000
0&
#3245000
b1111 1
b101111 ?
1&
#3250000
0&
#3255000
b1110 1
b110000 ?
1&
#3260000
0&
#3265000
b1101 1
b110001 ?
1&
#3270000
0&
#3275000
b1100 1
b110010 ?
1&
#3280000
0&
#3285000
b1011 1
b110011 ?
1&
#3290000
0&
#3295000
b1010 1
b110100 ?
1&
#3300000
0&
#3305000
b1001 1
b110101 ?
1&
#3310000
0&
#3315000
b1000 1
b1 :
b1 7
b1 8
b110110 ?
1&
#3320000
0&
#3325000
b111 1
b11 :
b110111 ?
b11 7
b11 8
1&
#3330000
0&
#3335000
b110 1
b10000000 6
b0 :
b10000000 4
b0 7
b111 8
b111000 ?
1&
#3340000
0&
#3345000
b101 1
b1 :
b111001 ?
b1 7
b1 8
1&
#3350000
0&
#3355000
b100 1
b11 :
b11 7
b11 8
b111010 ?
1&
#3360000
0&
#3365000
b11 1
b110 :
b111011 ?
b110 7
b110 8
1&
#3370000
0&
#3375000
b10 1
b10001000 6
b10001000 4
b1101 8
b111100 ?
1&
#3380000
0&
#3385000
b1 1
b10001100 6
b101 :
b111101 ?
b10001100 4
b101 7
b1100 8
1&
#3390000
0&
#3395000
b0 1
b10001110 6
b11 :
b10001110 4
b11 7
b1010 8
b111110 ?
1&
#3400000
0&
#3405000
1#
0%
b110 !
b110 9
b10001110 "
b10001110 5
b110 :
b111111 ?
b110 7
b110 8
1&
#3410000
0&
#3415000
b1000000 ?
1&
#3420000
0&
#3425000
b0 =
b1111111111111111111111111111111111111111111111111111111111111111 <
b1 ;
b1111111111111111111111111111111111111111111111111111111111111111 >
1&
#3430000
0&
#3435000
1,
b1 '
b1 /
b1111111111111111111111111111111111111111111111111111111111111111 (
b1111111111111111111111111111111111111111111111111111111111111111 0
1&
#3440000
0&
#3445000
0,
1%
b111111 1
b0 :
b0 6
b1 2
b1111111111111111111111111111111111111111111111111111111111111111 3
0#
1&
#3450000
0&
#3455000
b111110 1
b1000000000000000000000000000000000000000000000000000000000000000 6
b0 7
b1000000000000000000000000000000000000000000000000000000000000000 4
b1 8
b0 ?
1&
#3460000
0&
#3465000
b111101 1
b1100000000000000000000000000000000000000000000000000000000000000 6
b1 ?
b1100000000000000000000000000000000000000000000000000000000000000 4
1&
#3470000
0&
#3475000
b111100 1
b1110000000000000000000000000000000000000000000000000000000000000 6
b1110000000000000000000000000000000000000000000000000000000000000 4
b10 ?
1&
#3480000
0&
#3485000
b111011 1
b1111000000000000000000000000000000000000000000000000000000000000 6
b11 ?
b1111000000000000000000000000000000000000000000000000000000000000 4
1&
#3490000
0&
#3495000
b111010 1
b1111100000000000000000000000000000000000000000000000000000000000 6
b1111100000000000000000000000000000000000000000000000000000000000 4
b100 ?
1&
#3500000
0&
#3505000
b111001 1
b1111110000000000000000000000000000000000000000000000000000000000 6
b101 ?
b1111110000000000000000000000000000000000000000000000000000000000 4
1&
#3510000
0&
#3515000
b111000 1
b1111111000000000000000000000000000000000000000000000000000000000 6
b1111111000000000000000000000000000000000000000000000000000000000 4
b110 ?
1&
#3520000
0&
#3525000
b110111 1
b1111111100000000000000000000000000000000000000000000000000000000 6
b111 ?
b1111111100000000000000000000000000000000000000000000000000000000 4
1&
#3530000
0&
#3535000
b110110 1
b1111111110000000000000000000000000000000000000000000000000000000 6
b1111111110000000000000000000000000000000000000000000000000000000 4
b1000 ?
1&
#3540000
0&
