Verilog Library/src/GcodeFetcher.v
module GcodeFetcher(
    input clk,
    input rst,
    input rewind,
    input cmd_ready,

    output reg cmd_valid,
    output reg cmd_last,
    output reg [7:0] cmd_speed,
    output reg signed [31:0] cmd_pos_x,
    output reg signed [31:0] cmd_pos_y,
    output reg signed [31:0] cmd_pos_z
    );

    localparam MAX_LINE = 905;

    reg [15:0] curr_line;
    reg [15:0] speed [0:MAX_LINE-1];
    reg signed [20:0] pos_x [0:MAX_LINE-1];
    reg signed [20:0] pos_y [0:MAX_LINE-1];
    reg signed [20:0] pos_z [0:MAX_LINE-1];

    wire cmd_transfer;
    wire current_is_last;

    assign cmd_transfer = cmd_valid && cmd_ready;
    assign current_is_last = (curr_line == (MAX_LINE - 1));

    always @(posedge clk) begin
        if (rst || rewind) begin
            curr_line <= 0;
            cmd_valid <= 1;
            cmd_last <= (MAX_LINE == 1);
            cmd_speed <= speed[0];
            cmd_pos_x <= pos_x[0];
            cmd_pos_y <= pos_y[0];
            cmd_pos_z <= pos_z[0];
        end else begin
            if (cmd_transfer) begin
                if (current_is_last) begin
                    cmd_valid <= 0;
                    cmd_last <= 0;
                end else begin
                    curr_line <= curr_line + 1;
                    cmd_valid <= 1;
                    cmd_last <= (curr_line + 1 == (MAX_LINE - 1));
                    cmd_speed <= speed[curr_line + 1];
                    cmd_pos_x <= pos_x[curr_line + 1];
                    cmd_pos_y <= pos_y[curr_line + 1];
                    cmd_pos_z <= pos_z[curr_line + 1];
                end
            end
        end
    end

    initial begin
        // X Y Z F
        // Note F speed is in mm/sec, max tested speed = 90
        $readmemh("E:/Git-Repos/CNC-FPGA/Hexfiles/kirby/pos_x.hex", pos_x);
        $readmemh("E:/Git-Repos/CNC-FPGA/Hexfiles/kirby/pos_y.hex", pos_y);
        $readmemh("E:/Git-Repos/CNC-FPGA/Hexfiles/kirby/pos_z.hex", pos_z);
        $readmemh("E:/Git-Repos/CNC-FPGA/Hexfiles/kirby/speed.hex", speed);
    end
endmodule

Verilog Library/tb/GcodeFetcher_tb.v
`timescale 1ns/1ps

module GcodeFetcher_tb;
    localparam MAX_LINE = 905;

    reg clk;
    reg rst;
    reg rewind;
    reg cmd_ready;

    wire cmd_valid;
    wire cmd_last;
    wire [7:0] cmd_speed;
    wire signed [31:0] cmd_pos_x;
    wire signed [31:0] cmd_pos_y;
    wire signed [31:0] cmd_pos_z;

    integer errors;
    integer idx;

    reg [15:0] ref_speed [0:MAX_LINE-1];
    reg signed [20:0] ref_pos_x [0:MAX_LINE-1];
    reg signed [20:0] ref_pos_y [0:MAX_LINE-1];
    reg signed [20:0] ref_pos_z [0:MAX_LINE-1];

    GcodeFetcher dut (
        .clk(clk),
        .rst(rst),
        .rewind(rewind),
        .cmd_ready(cmd_ready),
        .cmd_valid(cmd_valid),
        .cmd_last(cmd_last),
        .cmd_speed(cmd_speed),
        .cmd_pos_x(cmd_pos_x),
        .cmd_pos_y(cmd_pos_y),
        .cmd_pos_z(cmd_pos_z)
    );

    always #5 clk = ~clk;

    task expect_outputs;
        input [7:0] exp_speed;
        input signed [31:0] exp_x;
        input signed [31:0] exp_y;
        input signed [31:0] exp_z;
        input exp_valid;
        input exp_last;
        begin
            if (cmd_speed !== exp_speed ||
                cmd_pos_x !== exp_x ||
                cmd_pos_y !== exp_y ||
                cmd_pos_z !== exp_z ||
                cmd_valid !== exp_valid ||
                cmd_last !== exp_last) begin
                $display(
                    "FAIL: expected speed=%0d x=%0d y=%0d z=%0d valid=%0b last=%0b got speed=%0d x=%0d y=%0d z=%0d valid=%0b last=%0b",
                    exp_speed, exp_x, exp_y, exp_z, exp_valid, exp_last,
                    cmd_speed, cmd_pos_x, cmd_pos_y, cmd_pos_z, cmd_valid, cmd_last
                );
                errors = errors + 1;
            end
        end
    endtask

    task accept_command;
        begin
            @(posedge clk);
            cmd_ready <= 1'b1;
            @(posedge clk);
            cmd_ready <= 1'b0;
        end
    endtask

    task expect_done;
        begin
            if (cmd_valid !== 1'b0 || cmd_last !== 1'b0) begin
                $display(
                    "FAIL: expected feeder done, got valid=%0b last=%0b speed=%0d x=%0d y=%0d z=%0d",
                    cmd_valid, cmd_last, cmd_speed, cmd_pos_x, cmd_pos_y, cmd_pos_z
                );
                errors = errors + 1;
            end
        end
    endtask

    initial begin
        $dumpfile("outputs/GcodeFetcher_tb.vcd");
        $dumpvars(0, GcodeFetcher_tb);

        $readmemh("E:/Git-Repos/CNC-FPGA/Hexfiles/kirby/speed.hex", ref_speed);
        $readmemh("E:/Git-Repos/CNC-FPGA/Hexfiles/kirby/pos_x.hex", ref_pos_x);
        $readmemh("E:/Git-Repos/CNC-FPGA/Hexfiles/kirby/pos_y.hex", ref_pos_y);
        $readmemh("E:/Git-Repos/CNC-FPGA/Hexfiles/kirby/pos_z.hex", ref_pos_z);

        clk = 1'b0;
        rst = 1'b1;
        rewind = 1'b0;
        cmd_ready = 1'b0;
        errors = 0;

        repeat (2) @(posedge clk);
        rst = 1'b0;
        @(posedge clk);

        repeat (3) @(posedge clk);
        expect_outputs(
            ref_speed[0][7:0],
            ref_pos_x[0],
            ref_pos_y[0],
            ref_pos_z[0],
            1'b1,
            1'b0
        );

        for (idx = 0; idx < MAX_LINE; idx = idx + 1) begin
            expect_outputs(
                ref_speed[idx][7:0],
                ref_pos_x[idx],
                ref_pos_y[idx],
                ref_pos_z[idx],
                1'b1,
                (idx == MAX_LINE - 1)
            );

            accept_command();
            @(posedge clk);

            if (idx < MAX_LINE - 1) begin
                expect_outputs(
                    ref_speed[idx + 1][7:0],
                    ref_pos_x[idx + 1],
                    ref_pos_y[idx + 1],
                    ref_pos_z[idx + 1],
                    1'b1,
                    (idx + 1 == MAX_LINE - 1)
                );
            end
        end

        expect_done();

        @(posedge clk);
        rewind <= 1'b1;
        @(posedge clk);
        rewind <= 1'b0;
        @(posedge clk);
        expect_outputs(
            ref_speed[0][7:0],
            ref_pos_x[0],
            ref_pos_y[0],
            ref_pos_z[0],
            1'b1,
            1'b0
        );

        if (errors == 0) begin
            $display("ALL TESTS PASSED");
        end else begin
            $display("TESTS FAILED: %0d errors", errors);
        end

        $finish;
    end
endmodule

Verilog Library/outputs/GcodeFetcher_tb.vcd
$date
	Wed Mar 04 16:41:33 2026
$end
$version
	Icarus Verilog
$end
$timescale
	1ps
$end
$scope module GcodeFetcher_tb $end
$var wire 1 ! cmd_valid $end
$var wire 8 " cmd_speed [7:0] $end
$var wire 32 # cmd_pos_z [31:0] $end
$var wire 32 $ cmd_pos_y [31:0] $end
$var wire 32 % cmd_pos_x [31:0] $end
$var wire 1 & cmd_last $end
$var parameter 32 ' MAX_LINE $end
$var reg 1 ( clk $end
$var reg 1 ) cmd_ready $end
$var reg 1 * rewind $end
$var reg 1 + rst $end
$var integer 32 , errors [31:0] $end
$var integer 32 - idx [31:0] $end
$scope module dut $end
$var wire 1 ( clk $end
$var wire 1 ) cmd_ready $end
$var wire 1 . cmd_transfer $end
$var wire 1 * rewind $end
$var wire 1 + rst $end
$var wire 1 / current_is_last $end
$var parameter 32 0 MAX_LINE $end
$var reg 1 & cmd_last $end
$var reg 32 1 cmd_pos_x [31:0] $end
$var reg 32 2 cmd_pos_y [31:0] $end
$var reg 32 3 cmd_pos_z [31:0] $end
$var reg 8 4 cmd_speed [7:0] $end
$var reg 1 ! cmd_valid $end
$var reg 16 5 curr_line [15:0] $end
$upscope $end
$scope task accept_command $end
$upscope $end
$scope task expect_done $end
$upscope $end
$scope task expect_outputs $end
$var reg 1 6 exp_last $end
$var reg 8 7 exp_speed [7:0] $end
$var reg 1 8 exp_valid $end
$var reg 32 9 exp_x [31:0] $end
$var reg 32 : exp_y [31:0] $end
$var reg 32 ; exp_z [31:0] $end
$upscope $end
$upscope $end
$enddefinitions $end
$comment Show the parameter values. $end
$dumpall
b1110001001 0
b1110001001 '
$end
#0
$dumpvars
bx ;
bx :
bx 9
x8
bx 7
x6
bx 5
bx 4
bx 3
bx 2
bx 1
x/
0.
bx -
b0 ,
1+
0*
0)
0(
x&
bx %
bx $
bx #
bx "
x!
$end
#5000
b1001110001000 #
b1001110001000 3
b0 $
b0 2
b0 %
b0 1
b10110100 "
b10110100 4
0&
1!
0/
b0 5
1(
#10000
0(
#15000
0+
1(
#20000
0(
#25000
1(
#30000
0(
#35000
1(
#40000
0(
#45000
1(
#50000
0(
#55000
b0 -
06
18
b1001110001000 ;
b0 :
b0 9
b10110100 7
1(
#60000
0(
#65000
1.
1)
1(
#70000
0(
#75000
0.
0)
b1 5
1(
#80000
0(
#85000
b1 -
1(
#90000
0(
#95000
1.
1)
1(
#100000
0(
#105000
0.
0)
b101000011000010000 $
b101000011000010000 2
b100000100101111110 %
b100000100101111110 1
b10 5
1(
#110000
0(
#115000
b10 -
b101000011000010000 :
b100000100101111110 9
1(
#120000
0(
#125000
1.
1)
1(
#130000
0(
#135000
0.
0)
b0 #
b0 3
b11 5
1(
#140000
0(
#145000
b11 -
b0 ;
1(
#150000
0(
#155000
1.
1)
1(
#160000
0(
#165000
0.
0)
b101000010001000110 $
b101000010001000110 2
b100001000110001110 %
b100001000110001110 1
b100 5
1(
#170000
0(
#175000
b100 -
b101000010001000110 :
b100001000110001110 9
1(
#180000
0(
#185000
1.
1)
1(
#190000
0(
#195000
0.
0)
b100101101110110110 $
b100101101110110110 2
b100010101111000111 %
b100010101111000111 1
b101 5
1(
#200000
0(
#205000
b101 -
b100101101110110110 :
b100010101111000111 9
1(
#210000
0(
#215000
1.
1)
1(
#220000
0(
#225000
0.
0)
b100011101110110011 $
b100011101110110011 2
b100010101000101101 %
b100010101000101101 1
b110 5
1(
#230000
0(
#235000
b110 -
b100011101110110011 :
b100010101000101101 9
1(
#240000
0(
#245000
1.
1)
1(
#250000
0(
#255000
0.
0)
b100000000011111000 $
b100000000011111000 2
b11111010100100000 %
b11111010100100000 1
b111 5
1(
#260000
0(
#265000
b111 -
b100000000011111000 :
b11111010100100000 9
1(
#270000
0(
#275000
1.
1)
1(
#280000
0(
#285000
0.
0)
b11111011010001011 $
b11111011010001011 2
b11111000101010110 %
b11111000101010110 1
b1000 5
1(
#290000
0(
#295000
b1000 -
b11111011010001011 :
b11111000101010110 9
1(
#300000
0(
#305000
1.
1)
1(
#310000
0(
#315000
0.
0)
b10100011101001011 $
b10100011101001011 2
b11110011011101010 %
b11110011011101010 1
b1001 5
1(
#320000
0(
#325000
b1001 -
b10100011101001011 :
b11110011011101010 9
1(
#330000
0(
#335000
1.
1)
1(
#340000
0(
#345000
0.
0)
b10011111100111110 $
b10011111100111110 2
b11110001100100000 %
b11110001100100000 1
b1010 5
1(
#350000
0(
#355000
b1010 -
b10011111100111110 :
b11110001100100000 9
1(
#360000
0(
#365000
1.
1)
1(
#370000
0(
#375000
0.
0)
b10000100110111000 $
b10000100110111000 2
b11010100101010111 %
b11010100101010111 1
b1011 5
1(
#380000
0(
#385000
b1011 -
b10000100110111000 :
b11010100101010111 9
1(
#390000
0(
#395000
1.
1)
1(
#400000
0(
#405000
0.
0)
b1110110000110011 $
b1110110000110011 2
b11001010101101010 %
b11001010101101010 1
b1100 5
1(
#410000
0(
#415000
b1100 -
b1110110000110011 :
b11001010101101010 9
1(
#420000
0(
#425000
1.
1)
1(
#430000
0(
#435000
0.
0)
b1101010000110010 $
b1101010000110010 2
b10111111000111101 %
b10111111000111101 1
b1101 5
1(
#440000
0(
#445000
b1101 -
b1101010000110010 :
b10111111000111101 9
1(
#450000
0(
#455000
1.
1)
1(
#460000
0(
#465000
0.
0)
b1011110111101111 $
b1011110111101111 2
b10100011111000101 %
b10100011111000101 1
b1110 5
1(
#470000
0(
#475000
b1110 -
b1011110111101111 :
b10100011111000101 9
1(
#480000
0(
#485000
1.
1)
1(
#490000
0(
#495000
0.
0)
b1010001001110111 $
b1010001001110111 2
b10100010111100000 %
b10100010111100000 1
b1111 5
1(
#500000
0(
#505000
b1111 -
b1010001001110111 :
b10100010111100000 9
1(
#510000
0(
#515000
1.
1)
1(
#520000
0(
#525000
0.
0)
b1000011111110000 $
b1000011111110000 2
b10011110101011001 %
b10011110101011001 1
b10000 5
1(
#530000
0(
#535000
b10000 -
b1000011111110000 :
b10011110101011001 9
1(
#540000
0(
#545000
1.
1)
1(
#550000
0(
#555000
0.
0)
b110101110000101 $
b110101110000101 2
b10010111000110001 %
b10010111000110001 1
b10001 5
1(
#560000
0(
#565000
b10001 -
b110101110000101 :
b10010111000110001 9
1(
#570000
0(
#575000
1.
1)
1(
#580000
0(
#585000
0.
0)
b101011001111110 $
b101011001111110 2
b10001100111011000 %
b10001100111011000 1
b10010 5
1(
#590000
0(
#595000
b10010 -
b101011001111110 :
b10001100111011000 9
1(
#600000
0(
#605000
1.
1)
1(
#610000
0(
#615000
0.
0)
b100010101011011 $
b100010101011011 2
b10011000011001010 %
b10011000011001010 1
b10011 5
1(
#620000
0(
#625000
b10011 -
b100010101011011 :
b10011000011001010 9
1(
#630000
0(
#635000
1.
1)
1(
#640000
0(
#645000
0.
0)
b11000011001001 $
b11000011001001 2
b10100000100100011 %
b10100000100100011 1
b10100 5
1(
#650000
0(
#655000
b10100 -
b11000011001001 :
b10100000100100011 9
1(
#660000
0(
#665000
1.
1)
1(
#670000
0(
#675000
0.
0)
b10011101010000 $
b10011101010000 2
b10100010011101101 %
b10100010011101101 1
b10101 5
1(
#680000
0(
#685000
b10101 -
b10011101010000 :
b10100010011101101 9
1(
#690000
0(
#695000
1.
1)
1(
#700000
0(
#705000
0.
0)
b1110001101011 $
b1110001101011 2
b10100000110011100 %
b10100000110011100 1
b10110 5
1(
#710000
0(
#715000
b10110 -
b1110001101011 :
b10100000110011100 9
1(
#720000
0(
#725000
1.
1)
1(
#730000
0(
#735000
0.
0)
b1010011010111 $
b1010011010111 2
b10011000110000010 %
b10011000110000010 1
b10111 5
1(
#740000
0(
#745000
b10111 -
b1010011010111 :
b10011000110000010 9
1(
#750000
0(
#755000
1.
1)
1(
#760000
0(
#765000
0.
0)
b1001011110010 $
b1001011110010 2
b10001111110000010 %
b10001111110000010 1
b11000 5
1(
#770000
0(
#775000
b11000 -
b1001011110010 :
b10001111110000010 9
1(
#780000
0(
#785000
1.
1)
1(
#790000
0(
#795000
0.
0)
b1011010111100 $
b1011010111100 2
b1111001000001001 %
b1111001000001001 1
b11001 5
1(
#800000
0(
#805000
b11001 -
b1011010111100 :
b1111001000001001 9
1(
#810000
0(
#815000
1.
1)
1(
#820000
0(
#825000
0.
0)
b1111101000011 $
b1111101000011 2
b1101001011000111 %
b1101001011000111 1
b11010 5
1(
#830000
0(
#835000
b11010 -
b1111101000011 :
b1101001011000111 9
1(
#840000
0(
#845000
1.
1)
1(
#850000
0(
#855000
0.
0)
b10100000110101 $
b10100000110101 2
b1100011100111011 %
b1100011100111011 1
b11011 5
1(
#860000
0(
#865000
b11011 -
b10100000110101 :
b1100011100111011 9
1(
#870000
0(
#875000
1.
1)
1(
#880000
0(
#885000
0.
0)
b11010000011010 $
b11010000011010 2
b1100010111111101 %
b1100010111111101 1
b11100 5
1(
#890000
0(
#895000
b11100 -
b11010000011010 :
b1100010111111101 9
1(
#900000
0(
#905000
1.
1)
1(
#910000
0(
#915000
0.
0)
b11010100001101 $
b11010100001101 2
b1010111101000000 %
b1010111101000000 1
b11101 5
1(
#920000
0(
#925000
b11101 -
b11010100001101 :
b1010111101000000 9
1(
#930000
0(
#935000
1.
1)
1(
#940000
0(
#945000
0.
0)
b10111100100011 $
b10111100100011 2
b1010110011000100 %
b1010110011000100 1
b11110 5
1(
#950000
0(
#955000
b11110 -
b10111100100011 :
b1010110011000100 9
1(
#960000
0(
#965000
1.
1)
1(
#970000
0(
#975000
0.
0)
b10001111111111 $
b10001111111111 2
b1001001001011100 %
b1001001001011100 1
b11111 5
1(
#980000
0(
#985000
b11111 -
b10001111111111 :
b1001001001011100 9
1(
#990000
0(
#995000
1.
1)
1(
#1000000
0(
#1005000
0.
0)
b1111001010000 $
b1111001010000 2
b111010111110001 %
b111010111110001 1
b100000 5
1(
#1010000
0(
#1015000
b100000 -
b1111001010000 :
b111010111110001 9
1(
#1020000
0(
#1025000
1.
1)
1(
#1030000
0(
#1035000
0.
0)
b100011110000110 %
b100011110000110 1
b100001 5
1(
#1040000
0(
#1045000
b100001 -
b100011110000110 9
1(
#1050000
0(
#1055000
1.
1)
1(
#1060000
0(
#1065000
0.
0)
b10011011010111 $
b10011011010111 2
b10111101011110 %
b10111101011110 1
b100010 5
1(
#1070000
0(
#1075000
b100010 -
b10011011010111 :
b10111101011110 9
1(
#1080000
0(
#1085000
1.
1)
1(
#1090000
0(
#1095000
0.
0)
b10111011100100 $
b10111011100100 2
b10111001101011 %
b10111001101011 1
b100011 5
1(
#1100000
0(
#1105000
b100011 -
b10111011100100 :
b10111001101011 9
1(
#1110000
0(
#1115000
1.
1)
1(
#1120000
0(
#1125000
0.
0)
b100001100000000 $
b100001100000000 2
b11101010000101 %
b11101010000101 1
b100100 5
1(
#1130000
0(
#1135000
b100100 -
b100001100000000 :
b11101010000101 9
1(
#1140000
0(
#1145000
1.
1)
1(
#1150000
0(
#1155000
0.
0)
b101111100110100 $
b101111100110100 2
b101101011110001 %
b101101011110001 1
b100101 5
1(
#1160000
0(
#1165000
b100101 -
b101111100110100 :
b101101011110001 9
1(
#1170000
0(
#1175000
1.
1)
1(
#1180000
0(
#1185000
0.
0)
b111001110010010 $
b111001110010010 2
b100101001011101 %
b100101001011101 1
b100110 5
1(
#1190000
0(
#1195000
b100110 -
b111001110010010 :
b100101001011101 9
1(
#1200000
0(
#1205000
1.
1)
1(
#1210000
0(
#1215000
0.
0)
b110001110101100 $
b110001110101100 2
b11010010001111 %
b11010010001111 1
b100111 5
1(
#1220000
0(
#1225000
b100111 -
b110001110101100 :
b11010010001111 9
1(
#1230000
0(
#1235000
1.
1)
1(
#1240000
0(
#1245000
0.
0)
b110000010100000 $
b110000010100000 2
b10010101101011 %
b10010101101011 1
b101000 5
1(
#1250000
0(
#1255000
b101000 -
b110000010100000 :
b10010101101011 9
1(
#1260000
0(
#1265000
1.
1)
1(
#1270000
0(
#1275000
0.
0)
b110001101011000 $
b110001101011000 2
b1111001111001 %
b1111001111001 1
b101001 5
1(
#1280000
0(
#1285000
b101001 -
b110001101011000 :
b1111001111001 9
1(
#1290000
0(
#1295000
1.
1)
1(
#1300000
0(
#1305000
0.
0)
b110111001011100 $
b110111001011100 2
b1100010100001 %
b1100010100001 1
b101010 5
1(
#1310000
0(
#1315000
b101010 -
b110111001011100 :
b1100010100001 9
1(
#1320000
0(
#1325000
1.
1)
1(
#1330000
0(
#1335000
0.
0)
b1001000101101001 $
b1001000101101001 2
b1100110010100 %
b1100110010100 1
b101011 5
1(
#1340000
0(
#1345000
b101011 -
b1001000101101001 :
b1100110010100 9
1(
#1350000
0(
#1355000
1.
1)
1(
#1360000
0(
#1365000
0.
0)
b1010111001011010 $
b1010111001011010 2
b10001100011010 %
b10001100011010 1
b101100 5
1(
#1370000
0(
#1375000
b101100 -
b1010111001011010 :
b10001100011010 9
1(
#1380000
0(
#1385000
1.
1)
1(
#1390000
0(
#1395000
0.
0)
b1100101100110011 $
b1100101100110011 2
b11011111100100 %
b11011111100100 1
b101101 5
1(
#1400000
0(
#1405000
b101101 -
b1100101100110011 :
b11011111100100 9
1(
#1410000
0(
#1415000
1.
1)
1(
#1420000
0(
#1425000
0.
0)
b1110111100000000 $
b1110111100000000 2
b100000110010000 %
b100000110010000 1
b101110 5
1(
#1430000
0(
#1435000
b101110 -
b1110111100000000 :
b100000110010000 9
1(
#1440000
0(
#1445000
1.
1)
1(
#1450000
0(
#1455000
0.
0)
b10000101110111100 $
b10000101110111100 2
b101001001001011 %
b101001001001011 1
b101111 5
1(
#1460000
0(
#1465000
b101111 -
b10000101110111100 :
b101001001001011 9
1(
#1470000
0(
#1475000
1.
1)
1(
#1480000
0(
#1485000
0.
0)
b10010101100000100 $
b10010101100000100 2
b111010110110100 %
b111010110110100 1
b110000 5
1(
#1490000
0(
#1495000
b110000 -
b10010101100000100 :
b111010110110100 9
1(
#1500000
0(
#1505000
1.
1)
1(
#1510000
0(
#1515000
0.
0)
b10011111001001100 $
b10011111001001100 2
b1001111010101101 %
b1001111010101101 1
b110001 5
1(
#1520000
0(
#1525000
b110001 -
b10011111001001100 :
b1001111010101101 9
1(
#1530000
0(
#1535000
1.
1)
1(
#1540000
0(
#1545000
0.
0)
b10100001111111011 $
b10100001111111011 2
b1011110011111101 %
b1011110011111101 1
b110010 5
1(
#1550000
0(
#1555000
b110010 -
b10100001111111011 :
b1011110011111101 9
1(
#1560000
0(
#1565000
1.
1)
1(
#1570000
0(
#1575000
0.
0)
b10100001100001000 $
b10100001100001000 2
b1110000000001010 %
b1110000000001010 1
b110011 5
1(
#1580000
0(
#1585000
b110011 -
b10100001100001000 :
b1110000000001010 9
1(
#1590000
0(
#1595000
1.
1)
1(
#1600000
0(
#1605000
0.
0)
b10011100010011101 $
b10011100010011101 2
b10000000010111000 %
b10000000010111000 1
b110100 5
1(
#1610000
0(
#1615000
b110100 -
b10011100010011101 :
b10000000010111000 9
1(
#1620000
0(
#1625000
1.
1)
1(
#1630000
0(
#1635000
0.
0)
b10100011011010010 $
b10100011011010010 2
b10001001100110001 %
b10001001100110001 1
b110101 5
1(
#1640000
0(
#1645000
b110101 -
b10100011011010010 :
b10001001100110001 9
1(
#1650000
0(
#1655000
1.
1)
1(
#1660000
0(
#1665000
0.
0)
b10101000001001011 $
b10101000001001011 2
b10011100100010110 %
b10011100100010110 1
b110110 5
1(
#1670000
0(
#1675000
b110110 -
b10101000001001011 :
b10011100100010110 9
1(
#1680000
0(
#1685000
1.
1)
1(
#1690000
0(
#1695000
0.
0)
b10100110101110100 $
b10100110101110100 2
b10101010010001111 %
b10101010010001111 1
b110111 5
1(
#1700000
0(
#1705000
b110111 -
b10100110101110100 :
b10101010010001111 9
1(
#1710000
0(
#1715000
1.
1)
1(
#1720000
0(
#1725000
0.
0)
b10110011000010101 $
b10110011000010101 2
b10111000000000111 %
b10111000000000111 1
b111000 5
1(
#1730000
0(
#1735000
b111000 -
b10110011000010101 :
b10111000000000111 9
1(
#1740000
0(
#1745000
1.
1)
1(
#1750000
0(
#1755000
0.
0)
b10110101111000100 $
b10110101111000100 2
b10111110101001011 %
b10111110101001011 1
b111001 5
1(
#1760000
0(
#1765000
b111001 -
b10110101111000100 :
b10111110101001011 9
1(
#1770000
0(
#1775000
1.
1)
1(
#1780000
0(
#1785000
0.
0)
b10110101011010010 $
b10110101011010010 2
b11001000100101111 %
b11001000100101111 1
b111010 5
1(
#1790000
0(
#1795000
b111010 -
b10110101011010010 :
b11001000100101111 9
1(
#1800000
0(
#1805000
1.
1)
1(
#1810000
0(
#1815000
0.
0)
b11001001100010100 $
b11001001100010100 2
b11001100001001010 %
b11001100001001010 1
b111011 5
1(
#1820000
0(
#1825000
b111011 -
b11001001100010100 :
b11001100001001010 9
1(
#1830000
0(
#1835000
1.
1)
1(
#1840000
0(
#1845000
0.
0)
b11011110110110101 $
b11011110110110101 2
b11010110000101111 %
b11010110000101111 1
b111100 5
1(
#1850000
0(
#1855000
b111100 -
b11011110110110101 :
b11010110000101111 9
1(
#1860000
0(
#1865000
1.
1)
1(
#1870000
0(
#1875000
0.
0)
b11110110100010011 $
b11110110100010011 2
b11011010010110101 %
b11011010010110101 1
b111101 5
1(
#1880000
0(
#1885000
b111101 -
b11110110100010011 :
b11011010010110101 9
1(
#1890000
0(
#1895000
1.
1)
1(
#1900000
0(
#1905000
0.
0)
b100000001011011101 $
b100000001011011101 2
b11011001011010000 %
b11011001011010000 1
b111110 5
1(
#1910000
0(
#1915000
b111110 -
b100000001011011101 :
b11011001011010000 9
1(
#1920000
0(
#1925000
1.
1)
1(
#1930000
0(
#1935000
0.
0)
b100010110010001011 $
b100010110010001011 2
b11001111011101100 %
b11001111011101100 1
b111111 5
1(
#1940000
0(
#1945000
b111111 -
b100010110010001011 :
b11001111011101100 9
1(
#1950000
0(
#1955000
1.
1)
1(
#1960000
0(
#1965000
0.
0)
b100101010001100001 $
b100101010001100001 2
b11001001110011001 %
b11001001110011001 1
b1000000 5
1(
#1970000
0(
#1975000
b1000000 -
b100101010001100001 :
b11001001110011001 9
1(
#1980000
0(
#1985000
1.
1)
1(
#1990000
0(
#1995000
0.
0)
b100110101010100110 $
b100110101010100110 2
b11010010111000111 %
b11010010111000111 1
b1000001 5
1(
#2000000
0(
#2005000
b1000001 -
b100110101010100110 :
b11010010111000111 9
1(
#2010000
0(
#2015000
1.
1)
1(
#2020000
0(
#2025000
0.
0)
b100110101111101000 $
b100110101111101000 2
b11010110001110101 %
b11010110001110101 1
b1000010 5
1(
#2030000
0(
#2035000
b1000010 -
b100110101111101000 :
b11010110001110101 9
1(
#2040000
0(
#2045000
1.
1)
1(
#2050000
0(
#2055000
0.
0)
b100110001010001010 $
b100110001010001010 2
b11011000111011110 %
b11011000111011110 1
b1000011 5
1(
#2060000
0(
#2065000
b1000011 -
b100110001010001010 :
b11011000111011110 9
1(
#2070000
0(
#2075000
1.
1)
1(
#2080000
0(
#2085000
0.
0)
b100100001101000111 $
b100100001101000111 2
b11011000011101011 %
b11011000011101011 1
b1000100 5
1(
#2090000
0(
#2095000
b1000100 -
b100100001101000111 :
b11011000011101011 9
1(
#2100000
0(
#2105000
1.
1)
1(
#2110000
0(
#2115000
0.
0)
b100011111100000100 $
b100011111100000100 2
b11011010000111100 %
b11011010000111100 1
b1000101 5
1(
#2120000
0(
#2125000
b1000101 -
b100011111100000100 :
b11011010000111100 9
1(
#2130000
0(
#2135000
1.
1)
1(
#2140000
0(
#2145000
0.
0)
b100011101001000111 $
b100011101001000111 2
b11100101011111000 %
b11100101011111000 1
b1000110 5
1(
#2150000
0(
#2155000
b1000110 -
b100011101001000111 :
b11100101011111000 9
1(
#2160000
0(
#2165000
1.
1)
1(
#2170000
0(
#2175000
0.
0)
b100100000101100010 $
b100100000101100010 2
b11101001111111000 %
b11101001111111000 1
b1000111 5
1(
#2180000
0(
#2185000
b1000111 -
b100100000101100010 :
b11101001111111000 9
1(
#2190000
0(
#2195000
1.
1)
1(
#2200000
0(
#2205000
0.
0)
b100100111110011000 $
b100100111110011000 2
b11101100010110101 %
b11101100010110101 1
b1001000 5
1(
#2210000
0(
#2215000
b1001000 -
b100100111110011000 :
b11101100010110101 9
1(
#2220000
0(
#2225000
1.
1)
1(
#2230000
0(
#2235000
0.
0)
b100111000011000000 $
b100111000011000000 2
b11101010111011101 %
b11101010111011101 1
b1001001 5
1(
#2240000
0(
#2245000
b1001001 -
b100111000011000000 :
b11101010111011101 9
1(
#2250000
0(
#2255000
1.
1)
1(
#2260000
0(
#2265000
0.
0)
b100111010111110110 $
b100111010111110110 2
b11101111011011101 %
b11101111011011101 1
b1001010 5
1(
#2270000
0(
#2275000
b1001010 -
b100111010111110110 :
b11101111011011101 9
1(
#2280000
0(
#2285000
1.
1)
1(
#2290000
0(
#2295000
0.
0)
b100110011101000111 $
b100110011101000111 2
b11110101110100111 %
b11110101110100111 1
b1001011 5
1(
#2300000
0(
#2305000
b1001011 -
b100110011101000111 :
b11110101110100111 9
1(
#2310000
0(
#2315000
1.
1)
1(
#2320000
0(
#2325000
0.
0)
b100100011110001011 $
b100100011110001011 2
b11110110000100000 %
b11110110000100000 1
b1001100 5
1(
#2330000
0(
#2335000
b1001100 -
b100100011110001011 :
b11110110000100000 9
1(
#2340000
0(
#2345000
1.
1)
1(
#2350000
0(
#2355000
0.
0)
b100101011000111010 $
b100101011000111010 2
b11111110010110100 %
b11111110010110100 1
b1001101 5
1(
#2360000
0(
#2365000
b1001101 -
b100101011000111010 :
b11111110010110100 9
1(
#2370000
0(
#2375000
1.
1)
1(
#2380000
0(
#2385000
0.
0)
b100110101100010001 $
b100110101100010001 2
b11111111010011001 %
b11111111010011001 1
b1001110 5
1(
#2390000
0(
#2395000
b1001110 -
b100110101100010001 :
b11111111010011001 9
1(
#2400000
0(
#2405000
1.
1)
1(
#2410000
0(
#2415000
0.
0)
b100111001110010111 $
b100111001110010111 2
b11111010000101101 %
b11111010000101101 1
b1001111 5
1(
#2420000
0(
#2425000
b1001111 -
b100111001110010111 :
b11111010000101101 9
1(
#2430000
0(
#2435000
1.
1)
1(
#2440000
0(
#2445000
0.
0)
b100111111011110101 $
b100111111011110101 2
b11111001100111011 %
b11111001100111011 1
b1010000 5
1(
#2450000
0(
#2455000
b1010000 -
b100111111011110101 :
b11111001100111011 9
1(
#2460000
0(
#2465000
1.
1)
1(
#2470000
0(
#2475000
0.
0)
b101000010001010001 $
b101000010001010001 2
b11111101011011001 %
b11111101011011001 1
b1010001 5
1(
#2480000
0(
#2485000
b1010001 -
b101000010001010001 :
b11111101011011001 9
1(
#2490000
0(
#2495000
1.
1)
1(
#2500000
0(
#2505000
0.
0)
b100111111101101111 $
b100111111101101111 2
b100000001111001111 %
b100000001111001111 1
b1010010 5
1(
#2510000
0(
#2515000
b1010010 -
b100111111101101111 :
b100000001111001111 9
1(
#2520000
0(
#2525000
1.
1)
1(
#2530000
0(
#2535000
0.
0)
b101000011000010000 $
b101000011000010000 2
b100000100101111110 %
b100000100101111110 1
b1010011 5
1(
#2540000
0(
#2545000
b1010011 -
b101000011000010000 :
b100000100101111110 9
1(
#2550000
0(
#2555000
1.
1)
1(
#2560000
0(
#2565000
0.
0)
b1001110001000 #
b1001110001000 3
b1010100 5
1(
#2570000
0(
#2575000
b1010100 -
b1001110001000 ;
1(
#2580000
0(
#2585000
1.
1)
1(
#2590000
0(
#2595000
0.
0)
b101000010100011110 $
b101000010100011110 2
b100000101011101010 %
b100000101011101010 1
b1010101 5
1(
#2600000
0(
